{
"meta":{"test_sets":[],"test_metrics":[],"learn_metrics":[{"best_value":"Min","name":"RMSE"}],"launch_mode":"Train","parameters":"","iteration_count":1000,"learn_sets":["learn"],"name":"experiment"},
"iterations":[
{"learn":[14.61268541],"iteration":0,"passed_time":0.1366629693,"remaining_time":136.5263064},
{"learn":[14.23196558],"iteration":1,"passed_time":0.137411254,"remaining_time":68.56821576},
{"learn":[13.86674177],"iteration":2,"passed_time":0.1380739315,"remaining_time":45.8865699},
{"learn":[13.49946468],"iteration":3,"passed_time":0.1386510746,"remaining_time":34.52411759},
{"learn":[13.16661202],"iteration":4,"passed_time":0.1393286894,"remaining_time":27.72640918},
{"learn":[12.85632158],"iteration":5,"passed_time":0.1398662941,"remaining_time":23.17118272},
{"learn":[12.56784336],"iteration":6,"passed_time":0.1406484903,"remaining_time":19.95199298},
{"learn":[12.31617801],"iteration":7,"passed_time":0.1414834818,"remaining_time":17.54395174},
{"learn":[12.01509946],"iteration":8,"passed_time":0.142649589,"remaining_time":15.70730474},
{"learn":[11.71512571],"iteration":9,"passed_time":0.1434030805,"remaining_time":14.19690497},
{"learn":[11.43264457],"iteration":10,"passed_time":0.1440315341,"remaining_time":12.94974429},
{"learn":[11.17973129],"iteration":11,"passed_time":0.144615649,"remaining_time":11.90668843},
{"learn":[10.93746433],"iteration":12,"passed_time":0.1452037799,"remaining_time":11.02431775},
{"learn":[10.69387075],"iteration":13,"passed_time":0.1457314402,"remaining_time":10.26365714},
{"learn":[10.4615922],"iteration":14,"passed_time":0.1462972594,"remaining_time":9.606853366},
{"learn":[10.2299235],"iteration":15,"passed_time":0.146864245,"remaining_time":9.032151066},
{"learn":[10.01419731],"iteration":16,"passed_time":0.1480085364,"remaining_time":8.558375955},
{"learn":[9.795856918],"iteration":17,"passed_time":0.1492678522,"remaining_time":8.143390602},
{"learn":[9.60040151],"iteration":18,"passed_time":0.1506503569,"remaining_time":7.778315795},
{"learn":[9.418664989],"iteration":19,"passed_time":0.1512705267,"remaining_time":7.41225581},
{"learn":[9.249278645],"iteration":20,"passed_time":0.1518724751,"remaining_time":7.08015015},
{"learn":[9.090113396],"iteration":21,"passed_time":0.1525338332,"remaining_time":6.78082222},
{"learn":[8.909548708],"iteration":22,"passed_time":0.1531066331,"remaining_time":6.503703502},
{"learn":[8.740140208],"iteration":23,"passed_time":0.1536896931,"remaining_time":6.25004752},
{"learn":[8.59377682],"iteration":24,"passed_time":0.1543185742,"remaining_time":6.018424393},
{"learn":[8.453885414],"iteration":25,"passed_time":0.1550718427,"remaining_time":5.809229799},
{"learn":[8.317732234],"iteration":26,"passed_time":0.1564760195,"remaining_time":5.638932111},
{"learn":[8.180896085],"iteration":27,"passed_time":0.1576030826,"remaining_time":5.471078439},
{"learn":[8.053220863],"iteration":28,"passed_time":0.1582232303,"remaining_time":5.297750228},
{"learn":[7.924234474],"iteration":29,"passed_time":0.1587772431,"remaining_time":5.133797526},
{"learn":[7.818879511],"iteration":30,"passed_time":0.1593494792,"remaining_time":4.980956303},
{"learn":[7.719346395],"iteration":31,"passed_time":0.1599410914,"remaining_time":4.838218014},
{"learn":[7.624163594],"iteration":32,"passed_time":0.1606941439,"remaining_time":4.708825368},
{"learn":[7.524952543],"iteration":33,"passed_time":0.1612679273,"remaining_time":4.581906406},
{"learn":[7.424464745],"iteration":34,"passed_time":0.1618687877,"remaining_time":4.462953719},
{"learn":[7.327482321],"iteration":35,"passed_time":0.1628498379,"remaining_time":4.36075677},
{"learn":[7.238666841],"iteration":36,"passed_time":0.1640203217,"remaining_time":4.268961346},
{"learn":[7.158842395],"iteration":37,"passed_time":0.164937222,"remaining_time":4.175515988},
{"learn":[7.074348246],"iteration":38,"passed_time":0.1654954417,"remaining_time":4.077977423},
{"learn":[6.992269093],"iteration":39,"passed_time":0.166091903,"remaining_time":3.986205672},
{"learn":[6.925219745],"iteration":40,"passed_time":0.1666147199,"remaining_time":3.897158937},
{"learn":[6.86013671],"iteration":41,"passed_time":0.1671672089,"remaining_time":3.813004432},
{"learn":[6.786739622],"iteration":42,"passed_time":0.1676733006,"remaining_time":3.731705782},
{"learn":[6.73057926],"iteration":43,"passed_time":0.1681773532,"remaining_time":3.654035219},
{"learn":[6.666356486],"iteration":44,"passed_time":0.1687012173,"remaining_time":3.580214722},
{"learn":[6.606182832],"iteration":45,"passed_time":0.1693050135,"remaining_time":3.511238757},
{"learn":[6.547854615],"iteration":46,"passed_time":0.1701185781,"remaining_time":3.449425636},
{"learn":[6.49240675],"iteration":47,"passed_time":0.1713002396,"remaining_time":3.397454753},
{"learn":[6.431317261],"iteration":48,"passed_time":0.1720229773,"remaining_time":3.338650028},
{"learn":[6.377586395],"iteration":49,"passed_time":0.1726045099,"remaining_time":3.279485689},
{"learn":[6.327558015],"iteration":50,"passed_time":0.1731301351,"remaining_time":3.221578395},
{"learn":[6.282040317],"iteration":51,"passed_time":0.1737325116,"remaining_time":3.167277326},
{"learn":[6.237655841],"iteration":52,"passed_time":0.1743693337,"remaining_time":3.115618095},
{"learn":[6.192792003],"iteration":53,"passed_time":0.1749863573,"remaining_time":3.06550174},
{"learn":[6.150579347],"iteration":54,"passed_time":0.1755694395,"remaining_time":3.016602187},
{"learn":[6.115693845],"iteration":55,"passed_time":0.1762471156,"remaining_time":2.971022805},
{"learn":[6.078780782],"iteration":56,"passed_time":0.1769703112,"remaining_time":2.927771991},
{"learn":[6.045146957],"iteration":57,"passed_time":0.1785031133,"remaining_time":2.899136772},
{"learn":[6.008080327],"iteration":58,"passed_time":0.1794760353,"remaining_time":2.862490665},
{"learn":[5.977575734],"iteration":59,"passed_time":0.1799703591,"remaining_time":2.819535626},
{"learn":[5.948036502],"iteration":60,"passed_time":0.1805180038,"remaining_time":2.778793534},
{"learn":[5.914888282],"iteration":61,"passed_time":0.181023083,"remaining_time":2.738704062},
{"learn":[5.884957796],"iteration":62,"passed_time":0.1815854939,"remaining_time":2.700723934},
{"learn":[5.849539885],"iteration":63,"passed_time":0.182138386,"remaining_time":2.663773895},
{"learn":[5.821387627],"iteration":64,"passed_time":0.1826870701,"remaining_time":2.627883239},
{"learn":[5.797012279],"iteration":65,"passed_time":0.1831886903,"remaining_time":2.592397526},
{"learn":[5.768685095],"iteration":66,"passed_time":0.1838583529,"remaining_time":2.560296169},
{"learn":[5.755484587],"iteration":67,"passed_time":0.1843919021,"remaining_time":2.527253717},
{"learn":[5.731887055],"iteration":68,"passed_time":0.1854932764,"remaining_time":2.502815077},
{"learn":[5.707148487],"iteration":69,"passed_time":0.186302654,"remaining_time":2.475163832},
{"learn":[5.685365039],"iteration":70,"passed_time":0.1868853663,"remaining_time":2.445302891},
{"learn":[5.663541834],"iteration":71,"passed_time":0.1874413342,"remaining_time":2.41591053},
{"learn":[5.638108797],"iteration":72,"passed_time":0.1881078207,"remaining_time":2.388711641},
{"learn":[5.619204893],"iteration":73,"passed_time":0.1886726641,"remaining_time":2.360957932},
{"learn":[5.598472793],"iteration":74,"passed_time":0.1892209262,"remaining_time":2.333724756},
{"learn":[5.577007075],"iteration":75,"passed_time":0.1897296884,"remaining_time":2.306713581},
{"learn":[5.562637084],"iteration":76,"passed_time":0.190259704,"remaining_time":2.280645543},
{"learn":[5.54729991],"iteration":77,"passed_time":0.1910592432,"remaining_time":2.258418234},
{"learn":[5.530737623],"iteration":78,"passed_time":0.1917855579,"remaining_time":2.235879732},
{"learn":[5.513704873],"iteration":79,"passed_time":0.1927768745,"remaining_time":2.216934057},
{"learn":[5.501575529],"iteration":80,"passed_time":0.1934933723,"remaining_time":2.195313693},
{"learn":[5.484080734],"iteration":81,"passed_time":0.194075019,"remaining_time":2.172693506},
{"learn":[5.472178894],"iteration":82,"passed_time":0.1945711874,"remaining_time":2.149659987},
{"learn":[5.458923342],"iteration":83,"passed_time":0.1951122618,"remaining_time":2.12765276},
{"learn":[5.451382371],"iteration":84,"passed_time":0.1954304526,"remaining_time":2.103751342},
{"learn":[5.441410748],"iteration":85,"passed_time":0.1959800154,"remaining_time":2.082857373},
{"learn":[5.434047468],"iteration":86,"passed_time":0.1963324513,"remaining_time":2.060362391},
{"learn":[5.422107497],"iteration":87,"passed_time":0.1968403055,"remaining_time":2.039981348},
{"learn":[5.40731265],"iteration":88,"passed_time":0.1973775182,"remaining_time":2.020347405},
{"learn":[5.396360181],"iteration":89,"passed_time":0.198066139,"remaining_time":2.002668739},
{"learn":[5.383793239],"iteration":90,"passed_time":0.1986575515,"remaining_time":1.984392465},
{"learn":[5.369605034],"iteration":91,"passed_time":0.1992363024,"remaining_time":1.96637568},
{"learn":[5.357467333],"iteration":92,"passed_time":0.1997736693,"remaining_time":1.948330301},
{"learn":[5.341109968],"iteration":93,"passed_time":0.2002951774,"remaining_time":1.930504582},
{"learn":[5.330529276],"iteration":94,"passed_time":0.2009795299,"remaining_time":1.914594469},
{"learn":[5.319862075],"iteration":95,"passed_time":0.2015397408,"remaining_time":1.897832559},
{"learn":[5.313052243],"iteration":96,"passed_time":0.2020664535,"remaining_time":1.881092861},
{"learn":[5.299677207],"iteration":97,"passed_time":0.2026027077,"remaining_time":1.864771861},
{"learn":[5.287546698],"iteration":98,"passed_time":0.2031504494,"remaining_time":1.848874292},
{"learn":[5.279803754],"iteration":99,"passed_time":0.2037021365,"remaining_time":1.833319228},
{"learn":[5.272254612],"iteration":100,"passed_time":0.2042289897,"remaining_time":1.817840215},
{"learn":[5.268813888],"iteration":101,"passed_time":0.204516819,"remaining_time":1.800550034},
{"learn":[5.258113767],"iteration":102,"passed_time":0.2050831415,"remaining_time":1.78601532},
{"learn":[5.251018576],"iteration":103,"passed_time":0.2056816685,"remaining_time":1.772026682},
{"learn":[5.24171237],"iteration":104,"passed_time":0.2062413535,"remaining_time":1.757962013},
{"learn":[5.233984943],"iteration":105,"passed_time":0.2068124789,"remaining_time":1.744248643},
{"learn":[5.226240449],"iteration":106,"passed_time":0.2073598092,"remaining_time":1.730582333},
{"learn":[5.220541644],"iteration":107,"passed_time":0.2079195605,"remaining_time":1.717261555},
{"learn":[5.211712096],"iteration":108,"passed_time":0.2084915948,"remaining_time":1.70427533},
{"learn":[5.203388597],"iteration":109,"passed_time":0.2090509803,"remaining_time":1.691412477},
{"learn":[5.196026544],"iteration":110,"passed_time":0.2095395898,"remaining_time":1.678204462},
{"learn":[5.188716772],"iteration":111,"passed_time":0.2101717286,"remaining_time":1.666361563},
{"learn":[5.182163132],"iteration":112,"passed_time":0.2107461842,"remaining_time":1.654264295},
{"learn":[5.17764747],"iteration":113,"passed_time":0.2112911978,"remaining_time":1.642140362},
{"learn":[5.170548056],"iteration":114,"passed_time":0.2118582801,"remaining_time":1.630387634},
{"learn":[5.165901827],"iteration":115,"passed_time":0.2123183569,"remaining_time":1.618012306},
{"learn":[5.160333668],"iteration":116,"passed_time":0.2128665152,"remaining_time":1.606505409},
{"learn":[5.148953243],"iteration":117,"passed_time":0.2134052092,"remaining_time":1.595113513},
{"learn":[5.144729126],"iteration":118,"passed_time":0.2138682394,"remaining_time":1.583343857},
{"learn":[5.139939946],"iteration":119,"passed_time":0.2145849085,"remaining_time":1.573622663},
{"learn":[5.132898872],"iteration":120,"passed_time":0.2153612074,"remaining_time":1.564483482},
{"learn":[5.129073077],"iteration":121,"passed_time":0.2158824565,"remaining_time":1.553645876},
{"learn":[5.127123916],"iteration":122,"passed_time":0.2161638232,"remaining_time":1.541265634},
{"learn":[5.121282057],"iteration":123,"passed_time":0.2166974055,"remaining_time":1.530862316},
{"learn":[5.114489821],"iteration":124,"passed_time":0.2172366642,"remaining_time":1.520656649},
{"learn":[5.107777291],"iteration":125,"passed_time":0.2177661421,"remaining_time":1.510536573},
{"learn":[5.103518754],"iteration":126,"passed_time":0.218289408,"remaining_time":1.500524828},
{"learn":[5.101133351],"iteration":127,"passed_time":0.2186153939,"remaining_time":1.489317371},
{"learn":[5.096462705],"iteration":128,"passed_time":0.2191465637,"remaining_time":1.479664008},
{"learn":[5.08562082],"iteration":129,"passed_time":0.219672248,"remaining_time":1.470114275},
{"learn":[5.080483682],"iteration":130,"passed_time":0.2202018508,"remaining_time":1.460728308},
{"learn":[5.07437499],"iteration":131,"passed_time":0.2207089553,"remaining_time":1.451328585},
{"learn":[5.070683732],"iteration":132,"passed_time":0.2212129301,"remaining_time":1.442042183},
{"learn":[5.06432037],"iteration":133,"passed_time":0.2217193412,"remaining_time":1.432902608},
{"learn":[5.057436484],"iteration":134,"passed_time":0.222253405,"remaining_time":1.424068114},
{"learn":[5.053254656],"iteration":135,"passed_time":0.2227527152,"remaining_time":1.415134897},
{"learn":[5.04801663],"iteration":136,"passed_time":0.22325013,"remaining_time":1.406312863},
{"learn":[5.045680836],"iteration":137,"passed_time":0.223697955,"remaining_time":1.397301719},
{"learn":[5.041857933],"iteration":138,"passed_time":0.2242476804,"remaining_time":1.389044985},
{"learn":[5.035264888],"iteration":139,"passed_time":0.2247216657,"remaining_time":1.380433089},
{"learn":[5.028771948],"iteration":140,"passed_time":0.2252456108,"remaining_time":1.37224099},
{"learn":[5.024912247],"iteration":141,"passed_time":0.2257553405,"remaining_time":1.364071001},
{"learn":[5.02239068],"iteration":142,"passed_time":0.2263106473,"remaining_time":1.356281292},
{"learn":[5.017110572],"iteration":143,"passed_time":0.2268490147,"remaining_time":1.348491365},
{"learn":[5.010707886],"iteration":144,"passed_time":0.2274198431,"remaining_time":1.340992868},
{"learn":[5.004389868],"iteration":145,"passed_time":0.2279753778,"remaining_time":1.333499812},
{"learn":[4.997628683],"iteration":146,"passed_time":0.2285717182,"remaining_time":1.326337929},
{"learn":[4.991497851],"iteration":147,"passed_time":0.2291144983,"remaining_time":1.318956436},
{"learn":[4.988345253],"iteration":148,"passed_time":0.2296712064,"remaining_time":1.311746286},
{"learn":[4.98460423],"iteration":149,"passed_time":0.2301982204,"remaining_time":1.304456582},
{"learn":[4.982441783],"iteration":150,"passed_time":0.2307508537,"remaining_time":1.297400495},
{"learn":[4.977461771],"iteration":151,"passed_time":0.2313004062,"remaining_time":1.290412793},
{"learn":[4.973601586],"iteration":152,"passed_time":0.2318253596,"remaining_time":1.283373069},
{"learn":[4.968328804],"iteration":153,"passed_time":0.2323243304,"remaining_time":1.276275217},
{"learn":[4.9640736],"iteration":154,"passed_time":0.2328732379,"remaining_time":1.269534748},
{"learn":[4.960865882],"iteration":155,"passed_time":0.2333825732,"remaining_time":1.262659563},
{"learn":[4.957014156],"iteration":156,"passed_time":0.2339053053,"remaining_time":1.255937403},
{"learn":[4.952244852],"iteration":157,"passed_time":0.2344154985,"remaining_time":1.249226897},
{"learn":[4.949695675],"iteration":158,"passed_time":0.2349096349,"remaining_time":1.242509452},
{"learn":[4.946584698],"iteration":159,"passed_time":0.2354861127,"remaining_time":1.236302092},
{"learn":[4.940192834],"iteration":160,"passed_time":0.2359734314,"remaining_time":1.229700056},
{"learn":[4.936727994],"iteration":161,"passed_time":0.2364914162,"remaining_time":1.223332141},
{"learn":[4.932342063],"iteration":162,"passed_time":0.2369882946,"remaining_time":1.216927623},
{"learn":[4.925830838],"iteration":163,"passed_time":0.237508961,"remaining_time":1.210716411},
{"learn":[4.922571773],"iteration":164,"passed_time":0.2380127603,"remaining_time":1.204488817},
{"learn":[4.918395814],"iteration":165,"passed_time":0.2385375671,"remaining_time":1.198435729},
{"learn":[4.911142452],"iteration":166,"passed_time":0.2390594976,"remaining_time":1.1924345},
{"learn":[4.908276131],"iteration":167,"passed_time":0.2395556734,"remaining_time":1.186370954},
{"learn":[4.904584645],"iteration":168,"passed_time":0.2401117943,"remaining_time":1.180668054},
{"learn":[4.89795517],"iteration":169,"passed_time":0.2406505343,"remaining_time":1.174940844},
{"learn":[4.895556491],"iteration":170,"passed_time":0.2412155529,"remaining_time":1.169401715},
{"learn":[4.890591233],"iteration":171,"passed_time":0.2417333236,"remaining_time":1.163692977},
{"learn":[4.884629277],"iteration":172,"passed_time":0.2422257711,"remaining_time":1.157923195},
{"learn":[4.880550786],"iteration":173,"passed_time":0.2428822851,"remaining_time":1.152992917},
{"learn":[4.876384842],"iteration":174,"passed_time":0.2434065278,"remaining_time":1.147487917},
{"learn":[4.872638238],"iteration":175,"passed_time":0.2439397521,"remaining_time":1.142081566},
{"learn":[4.869137118],"iteration":176,"passed_time":0.2444590605,"remaining_time":1.136665575},
{"learn":[4.863587157],"iteration":177,"passed_time":0.2450140288,"remaining_time":1.131469279},
{"learn":[4.858028614],"iteration":178,"passed_time":0.2455364999,"remaining_time":1.12617579},
{"learn":[4.853838176],"iteration":179,"passed_time":0.2460438942,"remaining_time":1.120866629},
{"learn":[4.853462329],"iteration":180,"passed_time":0.2462952771,"remaining_time":1.11445211},
{"learn":[4.851573196],"iteration":181,"passed_time":0.2468348154,"remaining_time":1.109400434},
{"learn":[4.848442087],"iteration":182,"passed_time":0.2473308752,"remaining_time":1.104203962},
{"learn":[4.845547104],"iteration":183,"passed_time":0.247874428,"remaining_time":1.099269202},
{"learn":[4.839868817],"iteration":184,"passed_time":0.2484006535,"remaining_time":1.094305582},
{"learn":[4.836336958],"iteration":185,"passed_time":0.248927122,"remaining_time":1.089390738},
{"learn":[4.831124789],"iteration":186,"passed_time":0.2494513567,"remaining_time":1.084513117},
{"learn":[4.827407333],"iteration":187,"passed_time":0.249996944,"remaining_time":1.079774035},
{"learn":[4.824088918],"iteration":188,"passed_time":0.2505309219,"remaining_time":1.075029511},
{"learn":[4.820934539],"iteration":189,"passed_time":0.2510297105,"remaining_time":1.070179292},
{"learn":[4.816975227],"iteration":190,"passed_time":0.2515374516,"remaining_time":1.065412557},
{"learn":[4.812340486],"iteration":191,"passed_time":0.2520797149,"remaining_time":1.060835467},
{"learn":[4.806402747],"iteration":192,"passed_time":0.2526103029,"remaining_time":1.05625137},
{"learn":[4.801521788],"iteration":193,"passed_time":0.2531595504,"remaining_time":1.051786586},
{"learn":[4.797601172],"iteration":194,"passed_time":0.2536637644,"remaining_time":1.047176053},
{"learn":[4.792694629],"iteration":195,"passed_time":0.2541873093,"remaining_time":1.042686718},
{"learn":[4.789794613],"iteration":196,"passed_time":0.254692753,"remaining_time":1.038163861},
{"learn":[4.785367055],"iteration":197,"passed_time":0.2552213412,"remaining_time":1.033775332},
{"learn":[4.780376856],"iteration":198,"passed_time":0.2557708109,"remaining_time":1.029509646},
{"learn":[4.776691261],"iteration":199,"passed_time":0.2563459365,"remaining_time":1.025383746},
{"learn":[4.773470753],"iteration":200,"passed_time":0.2569054319,"remaining_time":1.021231045},
{"learn":[4.77207327],"iteration":201,"passed_time":0.2574332603,"remaining_time":1.01698882},
{"learn":[4.767347177],"iteration":202,"passed_time":0.2579593174,"remaining_time":1.012776236},
{"learn":[4.763983068],"iteration":203,"passed_time":0.2584969967,"remaining_time":1.008645144},
{"learn":[4.761588849],"iteration":204,"passed_time":0.2590294965,"remaining_time":1.004529023},
{"learn":[4.758558086],"iteration":205,"passed_time":0.2595173451,"remaining_time":1.000275592},
{"learn":[4.753678804],"iteration":206,"passed_time":0.260033226,"remaining_time":0.9961659335},
{"learn":[4.746510889],"iteration":207,"passed_time":0.2606428857,"remaining_time":0.992447911},
{"learn":[4.744840601],"iteration":208,"passed_time":0.2611938473,"remaining_time":0.9885374797},
{"learn":[4.741702222],"iteration":209,"passed_time":0.2617312994,"remaining_time":0.9846082216},
{"learn":[4.739352853],"iteration":210,"passed_time":0.2623143446,"remaining_time":0.9808816016},
{"learn":[4.735539287],"iteration":211,"passed_time":0.2628184419,"remaining_time":0.9768911899},
{"learn":[4.730726751],"iteration":212,"passed_time":0.2633410291,"remaining_time":0.9730018304},
{"learn":[4.726416092],"iteration":213,"passed_time":0.2639111336,"remaining_time":0.9693184628},
{"learn":[4.721293082],"iteration":214,"passed_time":0.2644384063,"remaining_time":0.9655076695},
{"learn":[4.718443695],"iteration":215,"passed_time":0.2649551383,"remaining_time":0.9616890204},
{"learn":[4.711627962],"iteration":216,"passed_time":0.2654692003,"remaining_time":0.9578911697},
{"learn":[4.709790764],"iteration":217,"passed_time":0.2659620209,"remaining_time":0.9540472491},
{"learn":[4.706913073],"iteration":218,"passed_time":0.2664832825,"remaining_time":0.950335359},
{"learn":[4.703846389],"iteration":219,"passed_time":0.2669936833,"remaining_time":0.946613968},
{"learn":[4.701001135],"iteration":220,"passed_time":0.2674884429,"remaining_time":0.9428665025},
{"learn":[4.700380864],"iteration":221,"passed_time":0.267974611,"remaining_time":0.9391182312},
{"learn":[4.695837486],"iteration":222,"passed_time":0.2684853682,"remaining_time":0.9354848929},
{"learn":[4.691242996],"iteration":223,"passed_time":0.2690056997,"remaining_time":0.9319126025},
{"learn":[4.690284609],"iteration":224,"passed_time":0.269512071,"remaining_time":0.9283193555},
{"learn":[4.68827119],"iteration":225,"passed_time":0.2700188099,"remaining_time":0.9247546853},
{"learn":[4.686922425],"iteration":226,"passed_time":0.2707264589,"remaining_time":0.9219011135},
{"learn":[4.686085874],"iteration":227,"passed_time":0.2713181263,"remaining_time":0.9186736559},
{"learn":[4.683230741],"iteration":228,"passed_time":0.2718684612,"remaining_time":0.9153300594},
{"learn":[4.6773487],"iteration":229,"passed_time":0.2724804135,"remaining_time":0.9122170366},
{"learn":[4.671462906],"iteration":230,"passed_time":0.2730421852,"remaining_time":0.9089586165},
{"learn":[4.664799601],"iteration":231,"passed_time":0.2735917085,"remaining_time":0.9056828972},
{"learn":[4.660979386],"iteration":232,"passed_time":0.2741260207,"remaining_time":0.902380506},
{"learn":[4.656281279],"iteration":233,"passed_time":0.2746552148,"remaining_time":0.8990850193},
{"learn":[4.651997094],"iteration":234,"passed_time":0.2751715325,"remaining_time":0.8957711588},
{"learn":[4.650151977],"iteration":235,"passed_time":0.2757191154,"remaining_time":0.8925822211},
{"learn":[4.648478046],"iteration":236,"passed_time":0.2762116885,"remaining_time":0.889238474},
{"learn":[4.646364602],"iteration":237,"passed_time":0.276749299,"remaining_time":0.8860628818},
{"learn":[4.642635873],"iteration":238,"passed_time":0.2772882518,"remaining_time":0.8829136385},
{"learn":[4.640860821],"iteration":239,"passed_time":0.2777938954,"remaining_time":0.8796806687},
{"learn":[4.639446822],"iteration":240,"passed_time":0.278257346,"remaining_time":0.8763374508},
{"learn":[4.637120072],"iteration":241,"passed_time":0.2787506423,"remaining_time":0.873111516},
{"learn":[4.633769267],"iteration":242,"passed_time":0.2792857841,"remaining_time":0.8700384303},
{"learn":[4.630491517],"iteration":243,"passed_time":0.2798258608,"remaining_time":0.8670014376},
{"learn":[4.627813333],"iteration":244,"passed_time":0.2803414228,"remaining_time":0.8639092826},
{"learn":[4.622496304],"iteration":245,"passed_time":0.2808567731,"remaining_time":0.8608374264},
{"learn":[4.618979301],"iteration":246,"passed_time":0.2814014726,"remaining_time":0.8578757445},
{"learn":[4.616563458],"iteration":247,"passed_time":0.2819278139,"remaining_time":0.8548778872},
{"learn":[4.614759385],"iteration":248,"passed_time":0.2824326787,"remaining_time":0.8518351072},
{"learn":[4.61251363],"iteration":249,"passed_time":0.2829384975,"remaining_time":0.8488154924},
{"learn":[4.608796693],"iteration":250,"passed_time":0.2834404635,"remaining_time":0.8458044109},
{"learn":[4.60847774],"iteration":251,"passed_time":0.2839320325,"remaining_time":0.8427823821},
{"learn":[4.605195659],"iteration":252,"passed_time":0.2845365477,"remaining_time":0.8401138383},
{"learn":[4.60103766],"iteration":253,"passed_time":0.2850674709,"remaining_time":0.8372454067},
{"learn":[4.599325598],"iteration":254,"passed_time":0.2855385734,"remaining_time":0.834220538},
{"learn":[4.597012808],"iteration":255,"passed_time":0.2860493107,"remaining_time":0.8313308093},
{"learn":[4.594161533],"iteration":256,"passed_time":0.2865992024,"remaining_time":0.8285727913},
{"learn":[4.592197259],"iteration":257,"passed_time":0.2870830765,"remaining_time":0.8256420262},
{"learn":[4.58952828],"iteration":258,"passed_time":0.2876266379,"remaining_time":0.8229009217},
{"learn":[4.585816572],"iteration":259,"passed_time":0.2881401285,"remaining_time":0.8200911349},
{"learn":[4.582934052],"iteration":260,"passed_time":0.2886783385,"remaining_time":0.8173689353},
{"learn":[4.582234842],"iteration":261,"passed_time":0.2891989132,"remaining_time":0.8146137327},
{"learn":[4.57571562],"iteration":262,"passed_time":0.2897405587,"remaining_time":0.8119345696},
{"learn":[4.571197349],"iteration":263,"passed_time":0.2902709285,"remaining_time":0.8092401644},
{"learn":[4.56723703],"iteration":264,"passed_time":0.2907783817,"remaining_time":0.8064985303},
{"learn":[4.560335567],"iteration":265,"passed_time":0.2913049655,"remaining_time":0.8038264839},
{"learn":[4.554709345],"iteration":266,"passed_time":0.2918342628,"remaining_time":0.8011779574},
{"learn":[4.552806306],"iteration":267,"passed_time":0.2923502423,"remaining_time":0.7985088708},
{"learn":[4.550766241],"iteration":268,"passed_time":0.2928520216,"remaining_time":0.7958172037},
{"learn":[4.549216045],"iteration":269,"passed_time":0.2933652007,"remaining_time":0.7931725797},
{"learn":[4.547687452],"iteration":270,"passed_time":0.2938785874,"remaining_time":0.7905442444},
{"learn":[4.545642435],"iteration":271,"passed_time":0.2944108895,"remaining_time":0.7879820867},
{"learn":[4.543930359],"iteration":272,"passed_time":0.2949322775,"remaining_time":0.7854057352},
{"learn":[4.541029943],"iteration":273,"passed_time":0.2954736749,"remaining_time":0.7828974013},
{"learn":[4.537781449],"iteration":274,"passed_time":0.2959820884,"remaining_time":0.7803164148},
{"learn":[4.53066128],"iteration":275,"passed_time":0.296501723,"remaining_time":0.7777798821},
{"learn":[4.526763956],"iteration":276,"passed_time":0.297031306,"remaining_time":0.7752838781},
{"learn":[4.522036004],"iteration":277,"passed_time":0.2975502583,"remaining_time":0.7727744118},
{"learn":[4.515307629],"iteration":278,"passed_time":0.2982683531,"remaining_time":0.7707938445},
{"learn":[4.51109143],"iteration":279,"passed_time":0.2988659072,"remaining_time":0.7685123328},
{"learn":[4.508233494],"iteration":280,"passed_time":0.2993873064,"remaining_time":0.7660479476},
{"learn":[4.502555629],"iteration":281,"passed_time":0.2999067697,"remaining_time":0.7635924136},
{"learn":[4.500081355],"iteration":282,"passed_time":0.3004740529,"remaining_time":0.7612717171},
{"learn":[4.495281743],"iteration":283,"passed_time":0.3010813441,"remaining_time":0.7590642338},
{"learn":[4.492138869],"iteration":284,"passed_time":0.3016547914,"remaining_time":0.7567830731},
{"learn":[4.491708261],"iteration":285,"passed_time":0.302172504,"remaining_time":0.7543747127},
{"learn":[4.489398865],"iteration":286,"passed_time":0.3027466101,"remaining_time":0.7521196272},
{"learn":[4.485796373],"iteration":287,"passed_time":0.3033805817,"remaining_time":0.7500242158},
{"learn":[4.479542205],"iteration":288,"passed_time":0.303958636,"remaining_time":0.7478013503},
{"learn":[4.475986993],"iteration":289,"passed_time":0.3046082208,"remaining_time":0.7457649544},
{"learn":[4.468661855],"iteration":290,"passed_time":0.3051610097,"remaining_time":0.7435022538},
{"learn":[4.463785664],"iteration":291,"passed_time":0.3057684953,"remaining_time":0.7413838859},
{"learn":[4.460445831],"iteration":292,"passed_time":0.3063452412,"remaining_time":0.7392016571},
{"learn":[4.45692492],"iteration":293,"passed_time":0.3069262121,"remaining_time":0.7370404956},
{"learn":[4.454031688],"iteration":294,"passed_time":0.3075095012,"remaining_time":0.7348955877},
{"learn":[4.451672391],"iteration":295,"passed_time":0.3080699885,"remaining_time":0.7327069998},
{"learn":[4.45031553],"iteration":296,"passed_time":0.3085722615,"remaining_time":0.730391582},
{"learn":[4.446782666],"iteration":297,"passed_time":0.3090929118,"remaining_time":0.7281316245},
{"learn":[4.444369689],"iteration":298,"passed_time":0.3096136367,"remaining_time":0.7258834759},
{"learn":[4.44411683],"iteration":299,"passed_time":0.3100930107,"remaining_time":0.7235503583},
{"learn":[4.440876943],"iteration":300,"passed_time":0.3106230427,"remaining_time":0.7213471987},
{"learn":[4.439336453],"iteration":301,"passed_time":0.3111150989,"remaining_time":0.7190673479},
{"learn":[4.436666901],"iteration":302,"passed_time":0.3117549218,"remaining_time":0.7171392095},
{"learn":[4.433043336],"iteration":303,"passed_time":0.3123653056,"remaining_time":0.7151521471},
{"learn":[4.431419305],"iteration":304,"passed_time":0.3129314912,"remaining_time":0.713073398},
{"learn":[4.428859646],"iteration":305,"passed_time":0.3134512782,"remaining_time":0.7108993042},
{"learn":[4.424552441],"iteration":306,"passed_time":0.3139997698,"remaining_time":0.7088007833},
{"learn":[4.422706391],"iteration":307,"passed_time":0.3145136129,"remaining_time":0.706634481},
{"learn":[4.421427994],"iteration":308,"passed_time":0.31506361,"remaining_time":0.7045597233},
{"learn":[4.418733158],"iteration":309,"passed_time":0.3156117223,"remaining_time":0.7024906078},
{"learn":[4.415656941],"iteration":310,"passed_time":0.3162155921,"remaining_time":0.7005548005},
{"learn":[4.410747417],"iteration":311,"passed_time":0.3167659029,"remaining_time":0.6985094269},
{"learn":[4.408126521],"iteration":312,"passed_time":0.3173041006,"remaining_time":0.6964470196},
{"learn":[4.407843853],"iteration":313,"passed_time":0.317865854,"remaining_time":0.6944457829},
{"learn":[4.405219398],"iteration":314,"passed_time":0.3184211126,"remaining_time":0.6924395622},
{"learn":[4.402708465],"iteration":315,"passed_time":0.3189623775,"remaining_time":0.6904122349},
{"learn":[4.40104971],"iteration":316,"passed_time":0.3194879011,"remaining_time":0.6883603673},
{"learn":[4.400830038],"iteration":317,"passed_time":0.3200062514,"remaining_time":0.6863027152},
{"learn":[4.39784288],"iteration":318,"passed_time":0.3205028701,"remaining_time":0.6842083213},
{"learn":[4.393741845],"iteration":319,"passed_time":0.3210851008,"remaining_time":0.6823058393},
{"learn":[4.393425936],"iteration":320,"passed_time":0.321582256,"remaining_time":0.6802316255},
{"learn":[4.390505974],"iteration":321,"passed_time":0.322124121,"remaining_time":0.678261348},
{"learn":[4.390305136],"iteration":322,"passed_time":0.3226412862,"remaining_time":0.6762481449},
{"learn":[4.38568203],"iteration":323,"passed_time":0.3231765119,"remaining_time":0.6742818582},
{"learn":[4.383057135],"iteration":324,"passed_time":0.3237473319,"remaining_time":0.6723983048},
{"learn":[4.380662684],"iteration":325,"passed_time":0.3242964599,"remaining_time":0.670477957},
{"learn":[4.37805727],"iteration":326,"passed_time":0.3248335205,"remaining_time":0.66854116},
{"learn":[4.373708319],"iteration":327,"passed_time":0.3253650998,"remaining_time":0.6666016678},
{"learn":[4.36887921],"iteration":328,"passed_time":0.3259976221,"remaining_time":0.6648766092},
{"learn":[4.367895929],"iteration":329,"passed_time":0.3265577668,"remaining_time":0.6630112234},
{"learn":[4.362140573],"iteration":330,"passed_time":0.3270926106,"remaining_time":0.6611025875},
{"learn":[4.361931924],"iteration":331,"passed_time":0.3275940379,"remaining_time":0.6591349919},
{"learn":[4.359656377],"iteration":332,"passed_time":0.3280861777,"remaining_time":0.6571575993},
{"learn":[4.354281355],"iteration":333,"passed_time":0.3286241168,"remaining_time":0.6552804244},
{"learn":[4.348589447],"iteration":334,"passed_time":0.329221559,"remaining_time":0.6535293633},
{"learn":[4.346355698],"iteration":335,"passed_time":0.3297294229,"remaining_time":0.6516081452},
{"learn":[4.343894047],"iteration":336,"passed_time":0.330272823,"remaining_time":0.6497652274},
{"learn":[4.341561356],"iteration":337,"passed_time":0.3308515665,"remaining_time":0.6479992219},
{"learn":[4.338869061],"iteration":338,"passed_time":0.3313881006,"remaining_time":0.6461579188},
{"learn":[4.333720063],"iteration":339,"passed_time":0.331950598,"remaining_time":0.6443746902},
{"learn":[4.330892223],"iteration":340,"passed_time":0.3325057129,"remaining_time":0.6425843542},
{"learn":[4.328311474],"iteration":341,"passed_time":0.3330256207,"remaining_time":0.6407335042},
{"learn":[4.324580133],"iteration":342,"passed_time":0.3336003424,"remaining_time":0.638995408},
{"learn":[4.323354432],"iteration":343,"passed_time":0.334152076,"remaining_time":0.637220238},
{"learn":[4.323159553],"iteration":344,"passed_time":0.3346833329,"remaining_time":0.6354132842},
{"learn":[4.318639682],"iteration":345,"passed_time":0.3351752394,"remaining_time":0.6335393253},
{"learn":[4.312712208],"iteration":346,"passed_time":0.3357157494,"remaining_time":0.6317647964},
{"learn":[4.311461062],"iteration":347,"passed_time":0.3362107964,"remaining_time":0.6299121817},
{"learn":[4.311178356],"iteration":348,"passed_time":0.336683253,"remaining_time":0.6280252083},
{"learn":[4.311102505],"iteration":349,"passed_time":0.3371578325,"remaining_time":0.6261502604},
{"learn":[4.310232308],"iteration":350,"passed_time":0.337691912,"remaining_time":0.6243933074},
{"learn":[4.305128197],"iteration":351,"passed_time":0.3382252873,"remaining_time":0.6226420062},
{"learn":[4.304595496],"iteration":352,"passed_time":0.3387502146,"remaining_time":0.6208821214},
{"learn":[4.3004992],"iteration":353,"passed_time":0.3393038179,"remaining_time":0.6191815435},
{"learn":[4.297581524],"iteration":354,"passed_time":0.3399038555,"remaining_time":0.6175717939},
{"learn":[4.297355825],"iteration":355,"passed_time":0.3404262797,"remaining_time":0.615827315},
{"learn":[4.295758715],"iteration":356,"passed_time":0.3409419439,"remaining_time":0.6140775069},
{"learn":[4.292500657],"iteration":357,"passed_time":0.3414660603,"remaining_time":0.6123497507},
{"learn":[4.290797586],"iteration":358,"passed_time":0.3420233618,"remaining_time":0.6106879524},
{"learn":[4.286410608],"iteration":359,"passed_time":0.342564288,"remaining_time":0.6090031787},
{"learn":[4.280278245],"iteration":360,"passed_time":0.3431031418,"remaining_time":0.6073210737},
{"learn":[4.279941283],"iteration":361,"passed_time":0.3435833213,"remaining_time":0.6055418756},
{"learn":[4.274426275],"iteration":362,"passed_time":0.3440777193,"remaining_time":0.6037947857},
{"learn":[4.273567658],"iteration":363,"passed_time":0.3445592394,"remaining_time":0.6020320776},
{"learn":[4.269488271],"iteration":364,"passed_time":0.3450773698,"remaining_time":0.6003400818},
{"learn":[4.266838205],"iteration":365,"passed_time":0.345547978,"remaining_time":0.5985721805},
{"learn":[4.263456509],"iteration":366,"passed_time":0.3461184062,"remaining_time":0.5969835181},
{"learn":[4.260360204],"iteration":367,"passed_time":0.3466847381,"remaining_time":0.5953933545},
{"learn":[4.255120549],"iteration":368,"passed_time":0.3471985327,"remaining_time":0.5937189},
{"learn":[4.252582211],"iteration":369,"passed_time":0.3477195661,"remaining_time":0.592063045},
{"learn":[4.247857931],"iteration":370,"passed_time":0.3482248668,"remaining_time":0.5903866339},
{"learn":[4.245288911],"iteration":371,"passed_time":0.3487161413,"remaining_time":0.5886928408},
{"learn":[4.24048515],"iteration":372,"passed_time":0.34921214,"remaining_time":0.5870134365},
{"learn":[4.2378365],"iteration":373,"passed_time":0.3497164623,"remaining_time":0.5853542926},
{"learn":[4.236751063],"iteration":374,"passed_time":0.3502309226,"remaining_time":0.5837182043},
{"learn":[4.233240093],"iteration":375,"passed_time":0.3507244384,"remaining_time":0.5820533232},
{"learn":[4.230358421],"iteration":376,"passed_time":0.3512235338,"remaining_time":0.5804038769},
{"learn":[4.225853583],"iteration":377,"passed_time":0.3517447434,"remaining_time":0.5787969058},
{"learn":[4.224702126],"iteration":378,"passed_time":0.3522167018,"remaining_time":0.5771149652},
{"learn":[4.224361982],"iteration":379,"passed_time":0.3527231191,"remaining_time":0.5754956153},
{"learn":[4.223787954],"iteration":380,"passed_time":0.3532290076,"remaining_time":0.5738812485},
{"learn":[4.22144054],"iteration":381,"passed_time":0.3538714332,"remaining_time":0.5724935752},
{"learn":[4.217739335],"iteration":382,"passed_time":0.3543757369,"remaining_time":0.5708872837},
{"learn":[4.215611665],"iteration":383,"passed_time":0.3548900657,"remaining_time":0.5693028136},
{"learn":[4.210236863],"iteration":384,"passed_time":0.3554157791,"remaining_time":0.5677420888},
{"learn":[4.208454294],"iteration":385,"passed_time":0.3559142803,"remaining_time":0.5661434408},
{"learn":[4.207446501],"iteration":386,"passed_time":0.3564083101,"remaining_time":0.5645433955},
{"learn":[4.204985442],"iteration":387,"passed_time":0.3569283288,"remaining_time":0.5629900444},
{"learn":[4.202796622],"iteration":388,"passed_time":0.3574186305,"remaining_time":0.5613953296},
{"learn":[4.199774004],"iteration":389,"passed_time":0.3579139642,"remaining_time":0.5598141491},
{"learn":[4.199458358],"iteration":390,"passed_time":0.3583937097,"remaining_time":0.5582142436},
{"learn":[4.19751254],"iteration":391,"passed_time":0.3588884222,"remaining_time":0.556643267},
{"learn":[4.195201346],"iteration":392,"passed_time":0.359383086,"remaining_time":0.5550776927},
{"learn":[4.190593508],"iteration":393,"passed_time":0.3598960401,"remaining_time":0.5535456861},
{"learn":[4.187212054],"iteration":394,"passed_time":0.36036539,"remaining_time":0.551952053},
{"learn":[4.184984466],"iteration":395,"passed_time":0.3609023194,"remaining_time":0.5504671741},
{"learn":[4.182832144],"iteration":396,"passed_time":0.3613722812,"remaining_time":0.5488853541},
{"learn":[4.179752812],"iteration":397,"passed_time":0.3619762696,"remaining_time":0.547511845},
{"learn":[4.17878934],"iteration":398,"passed_time":0.3625067085,"remaining_time":0.5460314081},
{"learn":[4.174548229],"iteration":399,"passed_time":0.3630693808,"remaining_time":0.5446040712},
{"learn":[4.168872556],"iteration":400,"passed_time":0.3636216872,"remaining_time":0.5431655627},
{"learn":[4.163926494],"iteration":401,"passed_time":0.3641672186,"remaining_time":0.5417213848},
{"learn":[4.159485076],"iteration":402,"passed_time":0.3646846419,"remaining_time":0.5402400278},
{"learn":[4.155926102],"iteration":403,"passed_time":0.365241182,"remaining_time":0.5388211496},
{"learn":[4.153540115],"iteration":404,"passed_time":0.365792221,"remaining_time":0.5373984482},
{"learn":[4.150983044],"iteration":405,"passed_time":0.3663262414,"remaining_time":0.5359551414},
{"learn":[4.146539132],"iteration":406,"passed_time":0.3668180303,"remaining_time":0.5344547714},
{"learn":[4.144869174],"iteration":407,"passed_time":0.3673867608,"remaining_time":0.5330709863},
{"learn":[4.142825962],"iteration":408,"passed_time":0.3680715388,"remaining_time":0.5318588739},
{"learn":[4.142467378],"iteration":409,"passed_time":0.368756967,"remaining_time":0.5306502696},
{"learn":[4.141800768],"iteration":410,"passed_time":0.3695010159,"remaining_time":0.5295282198},
{"learn":[4.140107084],"iteration":411,"passed_time":0.3701658346,"remaining_time":0.5282949289},
{"learn":[4.136243196],"iteration":412,"passed_time":0.370717557,"remaining_time":0.5269036464},
{"learn":[4.133618439],"iteration":413,"passed_time":0.3712224308,"remaining_time":0.5254501074},
{"learn":[4.131053025],"iteration":414,"passed_time":0.3717269784,"remaining_time":0.5240006804},
{"learn":[4.128379975],"iteration":415,"passed_time":0.3722611498,"remaining_time":0.5225973834},
{"learn":[4.127068571],"iteration":416,"passed_time":0.3728109393,"remaining_time":0.5212200902},
{"learn":[4.125969877],"iteration":417,"passed_time":0.3733155605,"remaining_time":0.5197838665},
{"learn":[4.123893633],"iteration":418,"passed_time":0.3738446311,"remaining_time":0.518385992},
{"learn":[4.119643722],"iteration":419,"passed_time":0.3744374726,"remaining_time":0.5170803193},
{"learn":[4.11465686],"iteration":420,"passed_time":0.3749364669,"remaining_time":0.5156489651},
{"learn":[4.111565986],"iteration":421,"passed_time":0.3754619422,"remaining_time":0.5142583},
{"learn":[4.106322452],"iteration":422,"passed_time":0.376000335,"remaining_time":0.5128893459},
{"learn":[4.104222175],"iteration":423,"passed_time":0.3765174331,"remaining_time":0.5114953808},
{"learn":[4.103008002],"iteration":424,"passed_time":0.3770534967,"remaining_time":0.5101312014},
{"learn":[4.099176337],"iteration":425,"passed_time":0.3775791706,"remaining_time":0.5087569107},
{"learn":[4.096525716],"iteration":426,"passed_time":0.3781318721,"remaining_time":0.5074228635},
{"learn":[4.094967724],"iteration":427,"passed_time":0.3787104066,"remaining_time":0.506126992},
{"learn":[4.094683584],"iteration":428,"passed_time":0.3792376015,"remaining_time":0.5047661316},
{"learn":[4.091096563],"iteration":429,"passed_time":0.379756755,"remaining_time":0.5033984892},
{"learn":[4.089178677],"iteration":430,"passed_time":0.3803305133,"remaining_time":0.5021068726},
{"learn":[4.085335077],"iteration":431,"passed_time":0.3808783361,"remaining_time":0.5007844789},
{"learn":[4.084852122],"iteration":432,"passed_time":0.3815265748,"remaining_time":0.4995971545},
{"learn":[4.080322952],"iteration":433,"passed_time":0.3820673094,"remaining_time":0.4982721132},
{"learn":[4.077449519],"iteration":434,"passed_time":0.3825585695,"remaining_time":0.4968864179},
{"learn":[4.076568374],"iteration":435,"passed_time":0.3830417436,"remaining_time":0.4954943656},
{"learn":[4.076071793],"iteration":436,"passed_time":0.3835844295,"remaining_time":0.4941831438},
{"learn":[4.075027644],"iteration":437,"passed_time":0.3840926277,"remaining_time":0.4928311799},
{"learn":[4.07020837],"iteration":438,"passed_time":0.3846254219,"remaining_time":0.4915144913},
{"learn":[4.06833694],"iteration":439,"passed_time":0.3852077751,"remaining_time":0.4902644411},
{"learn":[4.063936568],"iteration":440,"passed_time":0.3857256629,"remaining_time":0.4889357042},
{"learn":[4.061734926],"iteration":441,"passed_time":0.3862605659,"remaining_time":0.4876321171},
{"learn":[4.060815619],"iteration":442,"passed_time":0.3868125081,"remaining_time":0.4863534244},
{"learn":[4.056407489],"iteration":443,"passed_time":0.3874070895,"remaining_time":0.4851314003},
{"learn":[4.05238936],"iteration":444,"passed_time":0.3879159809,"remaining_time":0.4838053245},
{"learn":[4.049685254],"iteration":445,"passed_time":0.3884617508,"remaining_time":0.4825287218},
{"learn":[4.045162016],"iteration":446,"passed_time":0.3890170515,"remaining_time":0.48126718},
{"learn":[4.042955482],"iteration":447,"passed_time":0.3895443425,"remaining_time":0.4799742791},
{"learn":[4.041467663],"iteration":448,"passed_time":0.3900562459,"remaining_time":0.4786659053},
{"learn":[4.038920476],"iteration":449,"passed_time":0.390562091,"remaining_time":0.4773536668},
{"learn":[4.036694383],"iteration":450,"passed_time":0.3911044163,"remaining_time":0.4760894114},
{"learn":[4.034999007],"iteration":451,"passed_time":0.3916667926,"remaining_time":0.47485266},
{"learn":[4.031928018],"iteration":452,"passed_time":0.3922469033,"remaining_time":0.4736403005},
{"learn":[4.028718143],"iteration":453,"passed_time":0.3927355674,"remaining_time":0.4723207484},
{"learn":[4.027401978],"iteration":454,"passed_time":0.3932599808,"remaining_time":0.4710476693},
{"learn":[4.025930598],"iteration":455,"passed_time":0.3937760121,"remaining_time":0.469767874},
{"learn":[4.021074523],"iteration":456,"passed_time":0.3943247765,"remaining_time":0.4685303144},
{"learn":[4.020268486],"iteration":457,"passed_time":0.3948999501,"remaining_time":0.4673270152},
{"learn":[4.017986361],"iteration":458,"passed_time":0.3956084544,"remaining_time":0.4662836031},
{"learn":[4.014814804],"iteration":459,"passed_time":0.3961721551,"remaining_time":0.4650716604},
{"learn":[4.009704796],"iteration":460,"passed_time":0.3967498315,"remaining_time":0.4638788702},
{"learn":[4.008440457],"iteration":461,"passed_time":0.3972989511,"remaining_time":0.4626554885},
{"learn":[4.004854849],"iteration":462,"passed_time":0.3978662482,"remaining_time":0.4614561021},
{"learn":[4.000898028],"iteration":463,"passed_time":0.3984376805,"remaining_time":0.4602642171},
{"learn":[3.996617985],"iteration":464,"passed_time":0.3989978914,"remaining_time":0.4590620901},
{"learn":[3.995443319],"iteration":465,"passed_time":0.3995400161,"remaining_time":0.4578419927},
{"learn":[3.990771995],"iteration":466,"passed_time":0.4000929172,"remaining_time":0.4566370982},
{"learn":[3.989249359],"iteration":467,"passed_time":0.4006042764,"remaining_time":0.4553877672},
{"learn":[3.986599538],"iteration":468,"passed_time":0.4013044905,"remaining_time":0.454355404},
{"learn":[3.985628919],"iteration":469,"passed_time":0.4018279149,"remaining_time":0.4531250956},
{"learn":[3.985086112],"iteration":470,"passed_time":0.4023611276,"remaining_time":0.4519087824},
{"learn":[3.98466839],"iteration":471,"passed_time":0.4028543361,"remaining_time":0.4506506133},
{"learn":[3.984233894],"iteration":472,"passed_time":0.4033416744,"remaining_time":0.4493891383},
{"learn":[3.981855845],"iteration":473,"passed_time":0.4038406108,"remaining_time":0.4481438001},
{"learn":[3.978684264],"iteration":474,"passed_time":0.4043459526,"remaining_time":0.4469086844},
{"learn":[3.974361269],"iteration":475,"passed_time":0.4048423501,"remaining_time":0.4456667888},
{"learn":[3.972074049],"iteration":476,"passed_time":0.4053933397,"remaining_time":0.4444878756},
{"learn":[3.97191982],"iteration":477,"passed_time":0.4058944952,"remaining_time":0.4432571684},
{"learn":[3.969616848],"iteration":478,"passed_time":0.4063800846,"remaining_time":0.4420125764},
{"learn":[3.968533527],"iteration":479,"passed_time":0.406917512,"remaining_time":0.4408273046},
{"learn":[3.967568753],"iteration":480,"passed_time":0.4074070326,"remaining_time":0.4395930352},
{"learn":[3.966232553],"iteration":481,"passed_time":0.4079236158,"remaining_time":0.4383909398},
{"learn":[3.961522393],"iteration":482,"passed_time":0.4085011048,"remaining_time":0.4372568761},
{"learn":[3.955829553],"iteration":483,"passed_time":0.4090561692,"remaining_time":0.4361012052},
{"learn":[3.954248095],"iteration":484,"passed_time":0.4096300295,"remaining_time":0.4349679694},
{"learn":[3.951922606],"iteration":485,"passed_time":0.4101911535,"remaining_time":0.4338235656},
{"learn":[3.94978202],"iteration":486,"passed_time":0.4107284166,"remaining_time":0.4326564224},
{"learn":[3.949518999],"iteration":487,"passed_time":0.4112575203,"remaining_time":0.4314833},
{"learn":[3.945431216],"iteration":488,"passed_time":0.4117858244,"remaining_time":0.430311976},
{"learn":[3.943249086],"iteration":489,"passed_time":0.4123243635,"remaining_time":0.4291539293},
{"learn":[3.941981548],"iteration":490,"passed_time":0.4128642714,"remaining_time":0.4279998252},
{"learn":[3.936600517],"iteration":491,"passed_time":0.4134338454,"remaining_time":0.4268788485},
{"learn":[3.934476885],"iteration":492,"passed_time":0.4139528127,"remaining_time":0.425708065},
{"learn":[3.93045798],"iteration":493,"passed_time":0.4145560233,"remaining_time":0.4246262101},
{"learn":[3.925977375],"iteration":494,"passed_time":0.4150838379,"remaining_time":0.42346937},
{"learn":[3.92457993],"iteration":495,"passed_time":0.4156919005,"remaining_time":0.4223966085},
{"learn":[3.919849146],"iteration":496,"passed_time":0.4162556331,"remaining_time":0.421280852},
{"learn":[3.919681964],"iteration":497,"passed_time":0.4167325531,"remaining_time":0.4200798025},
{"learn":[3.917633027],"iteration":498,"passed_time":0.4172686665,"remaining_time":0.418941086},
{"learn":[3.916616419],"iteration":499,"passed_time":0.4177720856,"remaining_time":0.4177720856},
{"learn":[3.912896166],"iteration":500,"passed_time":0.4182981858,"remaining_time":0.4166283327},
{"learn":[3.912769674],"iteration":501,"passed_time":0.4188139149,"remaining_time":0.4154767523},
{"learn":[3.909373788],"iteration":502,"passed_time":0.4193826815,"remaining_time":0.4143801048},
{"learn":[3.906706036],"iteration":503,"passed_time":0.4199930627,"remaining_time":0.4133265062},
{"learn":[3.903895664],"iteration":504,"passed_time":0.4205071938,"remaining_time":0.4121803187},
{"learn":[3.902982967],"iteration":505,"passed_time":0.42101507,"remaining_time":0.4110305229},
{"learn":[3.900905528],"iteration":506,"passed_time":0.4215623437,"remaining_time":0.409921569},
{"learn":[3.897463465],"iteration":507,"passed_time":0.4221199081,"remaining_time":0.4088247929},
{"learn":[3.895918033],"iteration":508,"passed_time":0.4226531298,"remaining_time":0.4077066537},
{"learn":[3.893921936],"iteration":509,"passed_time":0.4232107707,"remaining_time":0.4066142699},
{"learn":[3.890237934],"iteration":510,"passed_time":0.423792482,"remaining_time":0.4055470131},
{"learn":[3.887311613],"iteration":511,"passed_time":0.4243208726,"remaining_time":0.4044308317},
{"learn":[3.884869735],"iteration":512,"passed_time":0.424919368,"remaining_time":0.4033834936},
{"learn":[3.882101231],"iteration":513,"passed_time":0.4254154911,"remaining_time":0.4022411064},
{"learn":[3.88060368],"iteration":514,"passed_time":0.425962025,"remaining_time":0.4011487031},
{"learn":[3.877726076],"iteration":515,"passed_time":0.4264758565,"remaining_time":0.4000277414},
{"learn":[3.874938145],"iteration":516,"passed_time":0.4270378301,"remaining_time":0.3989541043},
{"learn":[3.874340833],"iteration":517,"passed_time":0.4276127124,"remaining_time":0.3978944544},
{"learn":[3.873105224],"iteration":518,"passed_time":0.4281642056,"remaining_time":0.396814996},
{"learn":[3.869800236],"iteration":519,"passed_time":0.4287420556,"remaining_time":0.3957618975},
{"learn":[3.867932518],"iteration":520,"passed_time":0.4293013218,"remaining_time":0.3946935377},
{"learn":[3.866666962],"iteration":521,"passed_time":0.4298322059,"remaining_time":0.3936011387},
{"learn":[3.865527652],"iteration":522,"passed_time":0.4303355485,"remaining_time":0.3924857679},
{"learn":[3.861900081],"iteration":523,"passed_time":0.4308883644,"remaining_time":0.3914176745},
{"learn":[3.858502887],"iteration":524,"passed_time":0.4315139558,"remaining_time":0.3904173886},
{"learn":[3.858335097],"iteration":525,"passed_time":0.4320430608,"remaining_time":0.3893315795},
{"learn":[3.855719306],"iteration":526,"passed_time":0.4325605854,"remaining_time":0.3882374893},
{"learn":[3.855137428],"iteration":527,"passed_time":0.4330940166,"remaining_time":0.3871598027},
{"learn":[3.851985706],"iteration":528,"passed_time":0.4336831497,"remaining_time":0.3861337684},
{"learn":[3.851051809],"iteration":529,"passed_time":0.4342016099,"remaining_time":0.3850467106},
{"learn":[3.850679146],"iteration":530,"passed_time":0.4347767195,"remaining_time":0.3840118294},
{"learn":[3.848179484],"iteration":531,"passed_time":0.4353320809,"remaining_time":0.3829613042},
{"learn":[3.844551071],"iteration":532,"passed_time":0.4358466957,"remaining_time":0.381876936},
{"learn":[3.841604794],"iteration":533,"passed_time":0.4363733371,"remaining_time":0.3808051968},
{"learn":[3.83969656],"iteration":534,"passed_time":0.4369149904,"remaining_time":0.379748543},
{"learn":[3.836811463],"iteration":535,"passed_time":0.4374826185,"remaining_time":0.3787162966},
{"learn":[3.834182551],"iteration":536,"passed_time":0.4380638561,"remaining_time":0.3776975146},
{"learn":[3.828012842],"iteration":537,"passed_time":0.4385987237,"remaining_time":0.3766405397},
{"learn":[3.826636176],"iteration":538,"passed_time":0.4391478719,"remaining_time":0.3755977161},
{"learn":[3.826189798],"iteration":539,"passed_time":0.4396546691,"remaining_time":0.374520644},
{"learn":[3.824104738],"iteration":540,"passed_time":0.4402036363,"remaining_time":0.3734814586},
{"learn":[3.82300218],"iteration":541,"passed_time":0.4407235226,"remaining_time":0.3724195081},
{"learn":[3.817146402],"iteration":542,"passed_time":0.4413197567,"remaining_time":0.3714238099},
{"learn":[3.814638044],"iteration":543,"passed_time":0.4418747424,"remaining_time":0.3703950046},
{"learn":[3.812979573],"iteration":544,"passed_time":0.4424317806,"remaining_time":0.3693696517},
{"learn":[3.811938825],"iteration":545,"passed_time":0.4429266669,"remaining_time":0.3682943347},
{"learn":[3.811479418],"iteration":546,"passed_time":0.4434646763,"remaining_time":0.3672568526},
{"learn":[3.80742981],"iteration":547,"passed_time":0.443961916,"remaining_time":0.3661875657},
{"learn":[3.805097043],"iteration":548,"passed_time":0.4445240068,"remaining_time":0.3651736376},
{"learn":[3.801577232],"iteration":549,"passed_time":0.4450350176,"remaining_time":0.3641195599},
{"learn":[3.799762083],"iteration":550,"passed_time":0.4455722238,"remaining_time":0.3630887995},
{"learn":[3.796393455],"iteration":551,"passed_time":0.4460801597,"remaining_time":0.3620360717},
{"learn":[3.793486459],"iteration":552,"passed_time":0.4466072318,"remaining_time":0.3610007823},
{"learn":[3.792006091],"iteration":553,"passed_time":0.4471196354,"remaining_time":0.3599555187},
{"learn":[3.78932128],"iteration":554,"passed_time":0.4476723301,"remaining_time":0.3589444809},
{"learn":[3.787581812],"iteration":555,"passed_time":0.4481988937,"remaining_time":0.3579142244},
{"learn":[3.785308865],"iteration":556,"passed_time":0.4487221644,"remaining_time":0.3568831577},
{"learn":[3.78465475],"iteration":557,"passed_time":0.4492210873,"remaining_time":0.3558346247},
{"learn":[3.780498869],"iteration":558,"passed_time":0.4497850642,"remaining_time":0.3548393798},
{"learn":[3.778734909],"iteration":559,"passed_time":0.4503685314,"remaining_time":0.353860989},
{"learn":[3.778652349],"iteration":560,"passed_time":0.4508519736,"remaining_time":0.3528057333},
{"learn":[3.777928006],"iteration":561,"passed_time":0.4514789178,"remaining_time":0.3518643523},
{"learn":[3.776131406],"iteration":562,"passed_time":0.4520016534,"remaining_time":0.3508432017},
{"learn":[3.772925617],"iteration":563,"passed_time":0.4525244784,"remaining_time":0.3498238875},
{"learn":[3.7727745],"iteration":564,"passed_time":0.4530260767,"remaining_time":0.3487899883},
{"learn":[3.771763073],"iteration":565,"passed_time":0.4535264443,"remaining_time":0.3477570262},
{"learn":[3.768738162],"iteration":566,"passed_time":0.4540727622,"remaining_time":0.3467610336},
{"learn":[3.767220794],"iteration":567,"passed_time":0.454579047,"remaining_time":0.3457361766},
{"learn":[3.766691102],"iteration":568,"passed_time":0.4551094519,"remaining_time":0.3447314126},
{"learn":[3.766259335],"iteration":569,"passed_time":0.455631581,"remaining_time":0.3437220698},
{"learn":[3.76116362],"iteration":570,"passed_time":0.4561380876,"remaining_time":0.3427026963},
{"learn":[3.758633056],"iteration":571,"passed_time":0.4567227055,"remaining_time":0.3417435628},
{"learn":[3.754603809],"iteration":572,"passed_time":0.4572510307,"remaining_time":0.3407437873},
{"learn":[3.754070549],"iteration":573,"passed_time":0.4577946645,"remaining_time":0.3397570158},
{"learn":[3.750534319],"iteration":574,"passed_time":0.4583268091,"remaining_time":0.3387632937},
{"learn":[3.746491516],"iteration":575,"passed_time":0.4588758664,"remaining_time":0.3377836239},
{"learn":[3.744210544],"iteration":576,"passed_time":0.4594603037,"remaining_time":0.3368313838},
{"learn":[3.742929991],"iteration":577,"passed_time":0.4600117956,"remaining_time":0.3358563629},
{"learn":[3.740402992],"iteration":578,"passed_time":0.4606064862,"remaining_time":0.3349142154},
{"learn":[3.739644243],"iteration":579,"passed_time":0.4611100419,"remaining_time":0.3339072718},
{"learn":[3.737529404],"iteration":580,"passed_time":0.4616602608,"remaining_time":0.332935713},
{"learn":[3.737196923],"iteration":581,"passed_time":0.4621753195,"remaining_time":0.3319403497},
{"learn":[3.733954464],"iteration":582,"passed_time":0.4627432099,"remaining_time":0.3309844228},
{"learn":[3.731608623],"iteration":583,"passed_time":0.463332547,"remaining_time":0.330045102},
{"learn":[3.729843952],"iteration":584,"passed_time":0.4638516137,"remaining_time":0.3290571277},
{"learn":[3.727223798],"iteration":585,"passed_time":0.464378763,"remaining_time":0.328076464},
{"learn":[3.725351667],"iteration":586,"passed_time":0.4649499748,"remaining_time":0.3271283468},
{"learn":[3.725026912],"iteration":587,"passed_time":0.4657493826,"remaining_time":0.3263414041},
{"learn":[3.721974565],"iteration":588,"passed_time":0.4663853687,"remaining_time":0.3254403846},
{"learn":[3.720269493],"iteration":589,"passed_time":0.4672800765,"remaining_time":0.3247200532},
{"learn":[3.718907466],"iteration":590,"passed_time":0.4678968963,"remaining_time":0.3238068199},
{"learn":[3.715602912],"iteration":591,"passed_time":0.468564942,"remaining_time":0.3229298924},
{"learn":[3.714463059],"iteration":592,"passed_time":0.4690990684,"remaining_time":0.3219617552},
{"learn":[3.710802077],"iteration":593,"passed_time":0.4696407949,"remaining_time":0.321000274},
{"learn":[3.708032435],"iteration":594,"passed_time":0.4701759396,"remaining_time":0.3200357236},
{"learn":[3.703788939],"iteration":595,"passed_time":0.4707101746,"remaining_time":0.3190719976},
{"learn":[3.702500944],"iteration":596,"passed_time":0.4712248399,"remaining_time":0.3180965},
{"learn":[3.698196925],"iteration":597,"passed_time":0.471722582,"remaining_time":0.3171111671},
{"learn":[3.69658891],"iteration":598,"passed_time":0.4722264951,"remaining_time":0.3161315936},
{"learn":[3.696124066],"iteration":599,"passed_time":0.4727016721,"remaining_time":0.3151344481},
{"learn":[3.693537052],"iteration":600,"passed_time":0.4732008174,"remaining_time":0.314154952},
{"learn":[3.691343275],"iteration":601,"passed_time":0.473704558,"remaining_time":0.3131800898},
{"learn":[3.690973831],"iteration":602,"passed_time":0.4742034744,"remaining_time":0.3122036142},
{"learn":[3.686151073],"iteration":603,"passed_time":0.4747111455,"remaining_time":0.3112344596},
{"learn":[3.683921982],"iteration":604,"passed_time":0.475200813,"remaining_time":0.3102550763},
{"learn":[3.679975271],"iteration":605,"passed_time":0.4756982018,"remaining_time":0.3092823293},
{"learn":[3.674047638],"iteration":606,"passed_time":0.4762035125,"remaining_time":0.3083162774},
{"learn":[3.673151794],"iteration":607,"passed_time":0.4766985074,"remaining_time":0.3073450903},
{"learn":[3.670953108],"iteration":608,"passed_time":0.4772763962,"remaining_time":0.3064286879},
{"learn":[3.6703947],"iteration":609,"passed_time":0.4777744892,"remaining_time":0.3054623784},
{"learn":[3.668433805],"iteration":610,"passed_time":0.4782947725,"remaining_time":0.3045117291},
{"learn":[3.668304956],"iteration":611,"passed_time":0.4788858122,"remaining_time":0.303607345},
{"learn":[3.667880012],"iteration":612,"passed_time":0.479471035,"remaining_time":0.3027003108},
{"learn":[3.667282264],"iteration":613,"passed_time":0.4800653813,"remaining_time":0.3018000606},
{"learn":[3.664611483],"iteration":614,"passed_time":0.4806293762,"remaining_time":0.3008818046},
{"learn":[3.662543394],"iteration":615,"passed_time":0.4811710571,"remaining_time":0.2999507888},
{"learn":[3.659041959],"iteration":616,"passed_time":0.4817065126,"remaining_time":0.2990171707},
{"learn":[3.656868545],"iteration":617,"passed_time":0.4822312393,"remaining_time":0.2980782094},
{"learn":[3.654785614],"iteration":618,"passed_time":0.4827630612,"remaining_time":0.2971449537},
{"learn":[3.654566096],"iteration":619,"passed_time":0.4832995767,"remaining_time":0.2962158696},
{"learn":[3.651007045],"iteration":620,"passed_time":0.4838815841,"remaining_time":0.2953158138},
{"learn":[3.648921786],"iteration":621,"passed_time":0.4844385597,"remaining_time":0.2944015684},
{"learn":[3.647655706],"iteration":622,"passed_time":0.4849472322,"remaining_time":0.2934592401},
{"learn":[3.647241144],"iteration":623,"passed_time":0.4854469468,"remaining_time":0.2925129038},
{"learn":[3.644195689],"iteration":624,"passed_time":0.4859657396,"remaining_time":0.2915794438},
{"learn":[3.642632246],"iteration":625,"passed_time":0.4865004388,"remaining_time":0.2906568117},
{"learn":[3.642523322],"iteration":626,"passed_time":0.486882008,"remaining_time":0.2896443206},
{"learn":[3.641494659],"iteration":627,"passed_time":0.4873846121,"remaining_time":0.2887055345},
{"learn":[3.63976496],"iteration":628,"passed_time":0.487891047,"remaining_time":0.287770395},
{"learn":[3.637945652],"iteration":629,"passed_time":0.4883944484,"remaining_time":0.2868348348},
{"learn":[3.636233667],"iteration":630,"passed_time":0.4888970155,"remaining_time":0.2859001564},
{"learn":[3.635304404],"iteration":631,"passed_time":0.4893831015,"remaining_time":0.284957249},
{"learn":[3.632234951],"iteration":632,"passed_time":0.4898873434,"remaining_time":0.2840263113},
{"learn":[3.631630987],"iteration":633,"passed_time":0.4904574165,"remaining_time":0.2831347231},
{"learn":[3.630301009],"iteration":634,"passed_time":0.4909905254,"remaining_time":0.2822229004},
{"learn":[3.629077964],"iteration":635,"passed_time":0.4914818086,"remaining_time":0.2812883307},
{"learn":[3.628004522],"iteration":636,"passed_time":0.4919702137,"remaining_time":0.2803535127},
{"learn":[3.625062876],"iteration":637,"passed_time":0.4924861321,"remaining_time":0.2794357051},
{"learn":[3.624917986],"iteration":638,"passed_time":0.4929580507,"remaining_time":0.2784942978},
{"learn":[3.622887087],"iteration":639,"passed_time":0.4937226171,"remaining_time":0.2777189721},
{"learn":[3.621220865],"iteration":640,"passed_time":0.4943665589,"remaining_time":0.2768761227},
{"learn":[3.621143844],"iteration":641,"passed_time":0.4950021652,"remaining_time":0.2760292447},
{"learn":[3.620822821],"iteration":642,"passed_time":0.4955694249,"remaining_time":0.2751450773},
{"learn":[3.619202826],"iteration":643,"passed_time":0.4961585667,"remaining_time":0.2742739903},
{"learn":[3.618204882],"iteration":644,"passed_time":0.4967044574,"remaining_time":0.2733799727},
{"learn":[3.614259666],"iteration":645,"passed_time":0.4972676439,"remaining_time":0.2724965107},
{"learn":[3.613415661],"iteration":646,"passed_time":0.4978541858,"remaining_time":0.2716267814},
{"learn":[3.611096773],"iteration":647,"passed_time":0.4984027776,"remaining_time":0.2707373113},
{"learn":[3.610820695],"iteration":648,"passed_time":0.4989802252,"remaining_time":0.2698644977},
{"learn":[3.609290065],"iteration":649,"passed_time":0.4995683027,"remaining_time":0.2689983169},
{"learn":[3.60897947],"iteration":650,"passed_time":0.5001144329,"remaining_time":0.2681105024},
{"learn":[3.606570702],"iteration":651,"passed_time":0.500694418,"remaining_time":0.2672418059},
{"learn":[3.606292637],"iteration":652,"passed_time":0.5012152454,"remaining_time":0.2663425577},
{"learn":[3.602753838],"iteration":653,"passed_time":0.5017160762,"remaining_time":0.2654338874},
{"learn":[3.599755869],"iteration":654,"passed_time":0.5022112572,"remaining_time":0.2645234866},
{"learn":[3.599509575],"iteration":655,"passed_time":0.5027019545,"remaining_time":0.2636120006},
{"learn":[3.595337722],"iteration":656,"passed_time":0.5032153721,"remaining_time":0.262713657},
{"learn":[3.595168561],"iteration":657,"passed_time":0.5037236172,"remaining_time":0.261813795},
{"learn":[3.59290559],"iteration":658,"passed_time":0.5042589843,"remaining_time":0.2609291558},
{"learn":[3.592015928],"iteration":659,"passed_time":0.5047800434,"remaining_time":0.2600382042},
{"learn":[3.590680403],"iteration":660,"passed_time":0.505300526,"remaining_time":0.2591480761},
{"learn":[3.590361532],"iteration":661,"passed_time":0.5058010897,"remaining_time":0.2582488947},
{"learn":[3.589069739],"iteration":662,"passed_time":0.5063083378,"remaining_time":0.2573543135},
{"learn":[3.585010186],"iteration":663,"passed_time":0.5068062074,"remaining_time":0.2564561531},
{"learn":[3.582997552],"iteration":664,"passed_time":0.5074061637,"remaining_time":0.2556106238},
{"learn":[3.582119256],"iteration":665,"passed_time":0.5079860363,"remaining_time":0.2547557599},
{"learn":[3.579019356],"iteration":666,"passed_time":0.5085215078,"remaining_time":0.2538795534},
{"learn":[3.57719559],"iteration":667,"passed_time":0.5090933621,"remaining_time":0.2530224494},
{"learn":[3.574050046],"iteration":668,"passed_time":0.5096592787,"remaining_time":0.2521632605},
{"learn":[3.572204518],"iteration":669,"passed_time":0.5101824219,"remaining_time":0.2512838794},
{"learn":[3.569508025],"iteration":670,"passed_time":0.5107392316,"remaining_time":0.2504220673},
{"learn":[3.566268704],"iteration":671,"passed_time":0.5112703226,"remaining_time":0.2495486098},
{"learn":[3.562564052],"iteration":672,"passed_time":0.511828991,"remaining_time":0.2486895692},
{"learn":[3.561173586],"iteration":673,"passed_time":0.5123586412,"remaining_time":0.2478173843},
{"learn":[3.559551904],"iteration":674,"passed_time":0.5129197398,"remaining_time":0.2469613562},
{"learn":[3.558593054],"iteration":675,"passed_time":0.5135045168,"remaining_time":0.2461175495},
{"learn":[3.555647008],"iteration":676,"passed_time":0.5140597837,"remaining_time":0.2452604286},
{"learn":[3.553100059],"iteration":677,"passed_time":0.5145437276,"remaining_time":0.2443703249},
{"learn":[3.55085578],"iteration":678,"passed_time":0.5150777518,"remaining_time":0.2435050933},
{"learn":[3.550737965],"iteration":679,"passed_time":0.5155796458,"remaining_time":0.2426257157},
{"learn":[3.549408772],"iteration":680,"passed_time":0.5161321779,"remaining_time":0.241771167},
{"learn":[3.547390589],"iteration":681,"passed_time":0.5166414962,"remaining_time":0.2408973545},
{"learn":[3.54723575],"iteration":682,"passed_time":0.5171557755,"remaining_time":0.2400269119},
{"learn":[3.543988891],"iteration":683,"passed_time":0.5176888962,"remaining_time":0.2391662152},
{"learn":[3.543868508],"iteration":684,"passed_time":0.5182149327,"remaining_time":0.2383032172},
{"learn":[3.542752124],"iteration":685,"passed_time":0.5187380177,"remaining_time":0.2374398507},
{"learn":[3.541334315],"iteration":686,"passed_time":0.5192858755,"remaining_time":0.2365887613},
{"learn":[3.540208266],"iteration":687,"passed_time":0.5198277232,"remaining_time":0.2357358279},
{"learn":[3.537730983],"iteration":688,"passed_time":0.5203595766,"remaining_time":0.2348792864},
{"learn":[3.53419867],"iteration":689,"passed_time":0.5209019787,"remaining_time":0.2340284252},
{"learn":[3.532628335],"iteration":690,"passed_time":0.5215536488,"remaining_time":0.2332273191},
{"learn":[3.532204987],"iteration":691,"passed_time":0.5220976782,"remaining_time":0.2323787354},
{"learn":[3.530618147],"iteration":692,"passed_time":0.5226323623,"remaining_time":0.2315268907},
{"learn":[3.528909306],"iteration":693,"passed_time":0.5232192847,"remaining_time":0.230698993},
{"learn":[3.526700678],"iteration":694,"passed_time":0.5237943605,"remaining_time":0.2298665899},
{"learn":[3.526439574],"iteration":695,"passed_time":0.524332143,"remaining_time":0.2290186372},
{"learn":[3.525784216],"iteration":696,"passed_time":0.5248514444,"remaining_time":0.2281635404},
{"learn":[3.524112693],"iteration":697,"passed_time":0.5254359244,"remaining_time":0.2273376062},
{"learn":[3.522813541],"iteration":698,"passed_time":0.5259816007,"remaining_time":0.2264956535},
{"learn":[3.519148203],"iteration":699,"passed_time":0.5265488152,"remaining_time":0.2256637779},
{"learn":[3.517236747],"iteration":700,"passed_time":0.5270678735,"remaining_time":0.2248121172},
{"learn":[3.515603888],"iteration":701,"passed_time":0.5276165579,"remaining_time":0.2239739804},
{"learn":[3.51263524],"iteration":702,"passed_time":0.5281623776,"remaining_time":0.2231354568},
{"learn":[3.51123442],"iteration":703,"passed_time":0.5286998442,"remaining_time":0.2222942527},
{"learn":[3.50828027],"iteration":704,"passed_time":0.5292521818,"remaining_time":0.2214601328},
{"learn":[3.508265537],"iteration":705,"passed_time":0.5295616346,"remaining_time":0.2205256665},
{"learn":[3.506774876],"iteration":706,"passed_time":0.5301028263,"remaining_time":0.2196890072},
{"learn":[3.50552068],"iteration":707,"passed_time":0.5306358011,"remaining_time":0.2188497937},
{"learn":[3.501973993],"iteration":708,"passed_time":0.531203516,"remaining_time":0.2180257026},
{"learn":[3.498880354],"iteration":709,"passed_time":0.531709096,"remaining_time":0.2171769547},
{"learn":[3.497370959],"iteration":710,"passed_time":0.5322412573,"remaining_time":0.2163399766},
{"learn":[3.496050455],"iteration":711,"passed_time":0.5327635934,"remaining_time":0.2154998805},
{"learn":[3.495630067],"iteration":712,"passed_time":0.533283911,"remaining_time":0.2146598632},
{"learn":[3.49550669],"iteration":713,"passed_time":0.5338336999,"remaining_time":0.2138325464},
{"learn":[3.493652375],"iteration":714,"passed_time":0.5343671041,"remaining_time":0.212999475},
{"learn":[3.491915684],"iteration":715,"passed_time":0.5349088023,"remaining_time":0.2121705305},
{"learn":[3.490303956],"iteration":716,"passed_time":0.5356455802,"remaining_time":0.2114193852},
{"learn":[3.488363853],"iteration":717,"passed_time":0.5362990524,"remaining_time":0.210635561},
{"learn":[3.485483936],"iteration":718,"passed_time":0.5369762708,"remaining_time":0.2098613798},
{"learn":[3.483763466],"iteration":719,"passed_time":0.5376909764,"remaining_time":0.2091020464},
{"learn":[3.481642352],"iteration":720,"passed_time":0.5383056893,"remaining_time":0.2083041433},
{"learn":[3.479826119],"iteration":721,"passed_time":0.538913472,"remaining_time":0.2075040792},
{"learn":[3.478588728],"iteration":722,"passed_time":0.5395967496,"remaining_time":0.2067334712},
{"learn":[3.475390887],"iteration":723,"passed_time":0.5403109927,"remaining_time":0.2059749088},
{"learn":[3.472636852],"iteration":724,"passed_time":0.5408975095,"remaining_time":0.2051680208},
{"learn":[3.47061883],"iteration":725,"passed_time":0.5415225137,"remaining_time":0.2043762655},
{"learn":[3.46953149],"iteration":726,"passed_time":0.5422500102,"remaining_time":0.2036234564},
{"learn":[3.467217162],"iteration":727,"passed_time":0.5429451087,"remaining_time":0.202858612},
{"learn":[3.465686216],"iteration":728,"passed_time":0.5435863236,"remaining_time":0.2020739282},
{"learn":[3.462631216],"iteration":729,"passed_time":0.544242927,"remaining_time":0.2012953292},
{"learn":[3.461451053],"iteration":730,"passed_time":0.5448123563,"remaining_time":0.2004849847},
{"learn":[3.458950469],"iteration":731,"passed_time":0.5454120638,"remaining_time":0.199686384},
{"learn":[3.458072145],"iteration":732,"passed_time":0.5460054086,"remaining_time":0.1988860083},
{"learn":[3.454364268],"iteration":733,"passed_time":0.5466067711,"remaining_time":0.1980891023},
{"learn":[3.453243406],"iteration":734,"passed_time":0.5474323864,"remaining_time":0.1973735815},
{"learn":[3.453017963],"iteration":735,"passed_time":0.5481001679,"remaining_time":0.1966011472},
{"learn":[3.45201581],"iteration":736,"passed_time":0.5486582851,"remaining_time":0.1957898629},
{"learn":[3.449510107],"iteration":737,"passed_time":0.5495786126,"remaining_time":0.1951078543},
{"learn":[3.447189189],"iteration":738,"passed_time":0.5501836051,"remaining_time":0.1943138307},
{"learn":[3.446423605],"iteration":739,"passed_time":0.5506987338,"remaining_time":0.1934887443},
{"learn":[3.445531987],"iteration":740,"passed_time":0.5512425948,"remaining_time":0.1926745372},
{"learn":[3.445328199],"iteration":741,"passed_time":0.5517920317,"remaining_time":0.1918629975},
{"learn":[3.443327544],"iteration":742,"passed_time":0.5524787003,"remaining_time":0.1910996312},
{"learn":[3.441475798],"iteration":743,"passed_time":0.553267801,"remaining_time":0.1903717165},
{"learn":[3.439046501],"iteration":744,"passed_time":0.554032971,"remaining_time":0.1896354465},
{"learn":[3.435899469],"iteration":745,"passed_time":0.554657702,"remaining_time":0.1888512819},
{"learn":[3.433988352],"iteration":746,"passed_time":0.5553740651,"remaining_time":0.1880985789},
{"learn":[3.433413263],"iteration":747,"passed_time":0.5559667437,"remaining_time":0.187304304},
{"learn":[3.429944699],"iteration":748,"passed_time":0.5565279105,"remaining_time":0.1865000074},
{"learn":[3.429291634],"iteration":749,"passed_time":0.5570839443,"remaining_time":0.1856946481},
{"learn":[3.429175603],"iteration":750,"passed_time":0.557604467,"remaining_time":0.1848781788},
{"learn":[3.428780323],"iteration":751,"passed_time":0.5581374974,"remaining_time":0.1840666215},
{"learn":[3.423893341],"iteration":752,"passed_time":0.5586647607,"remaining_time":0.1832539122},
{"learn":[3.421024316],"iteration":753,"passed_time":0.5592707313,"remaining_time":0.1824676391},
{"learn":[3.420969872],"iteration":754,"passed_time":0.5600219421,"remaining_time":0.1817289746},
{"learn":[3.419544785],"iteration":755,"passed_time":0.5607889127,"remaining_time":0.1809953634},
{"learn":[3.417057977],"iteration":756,"passed_time":0.5614030802,"remaining_time":0.1802126136},
{"learn":[3.415160245],"iteration":757,"passed_time":0.5620346325,"remaining_time":0.1794358589},
{"learn":[3.412854597],"iteration":758,"passed_time":0.5625537959,"remaining_time":0.1786238008},
{"learn":[3.410926347],"iteration":759,"passed_time":0.5633141509,"remaining_time":0.1778886792},
{"learn":[3.408963843],"iteration":760,"passed_time":0.5639480701,"remaining_time":0.1771137829},
{"learn":[3.407629634],"iteration":761,"passed_time":0.5647762236,"remaining_time":0.1763999228},
{"learn":[3.404384724],"iteration":762,"passed_time":0.5653677444,"remaining_time":0.1756122614},
{"learn":[3.403041656],"iteration":763,"passed_time":0.565910459,"remaining_time":0.1748100371},
{"learn":[3.401101731],"iteration":764,"passed_time":0.5664965939,"remaining_time":0.1740218295},
{"learn":[3.400890668],"iteration":765,"passed_time":0.5671607084,"remaining_time":0.173257971},
{"learn":[3.399289941],"iteration":766,"passed_time":0.5678173899,"remaining_time":0.1724921145},
{"learn":[3.399202366],"iteration":767,"passed_time":0.5686157962,"remaining_time":0.1717693551},
{"learn":[3.397447845],"iteration":768,"passed_time":0.5692772043,"remaining_time":0.171005246},
{"learn":[3.394655341],"iteration":769,"passed_time":0.5698624921,"remaining_time":0.1702186665},
{"learn":[3.393228229],"iteration":770,"passed_time":0.570416385,"remaining_time":0.1694232843},
{"learn":[3.389691197],"iteration":771,"passed_time":0.5709473751,"remaining_time":0.1686217636},
{"learn":[3.389626772],"iteration":772,"passed_time":0.5714628426,"remaining_time":0.1678163846},
{"learn":[3.388480222],"iteration":773,"passed_time":0.5720142481,"remaining_time":0.1670222482},
{"learn":[3.388215066],"iteration":774,"passed_time":0.5725776387,"remaining_time":0.1662322177},
{"learn":[3.386324358],"iteration":775,"passed_time":0.5730817367,"remaining_time":0.1654256559},
{"learn":[3.383913061],"iteration":776,"passed_time":0.5737356746,"remaining_time":0.164662877},
{"learn":[3.382839768],"iteration":777,"passed_time":0.5743175804,"remaining_time":0.1638798237},
{"learn":[3.381961844],"iteration":778,"passed_time":0.5751299337,"remaining_time":0.1631626641},
{"learn":[3.381521703],"iteration":779,"passed_time":0.5758157167,"remaining_time":0.1624095611},
{"learn":[3.380918963],"iteration":780,"passed_time":0.5765196808,"remaining_time":0.1616617287},
{"learn":[3.377139006],"iteration":781,"passed_time":0.5774041426,"remaining_time":0.1609643262},
{"learn":[3.376004372],"iteration":782,"passed_time":0.5779449647,"remaining_time":0.1601712099},
{"learn":[3.373826468],"iteration":783,"passed_time":0.5784981148,"remaining_time":0.1593821337},
{"learn":[3.373546786],"iteration":784,"passed_time":0.5790051864,"remaining_time":0.1585810383},
{"learn":[3.372109181],"iteration":785,"passed_time":0.579590389,"remaining_time":0.1578019634},
{"learn":[3.370764924],"iteration":786,"passed_time":0.580217329,"remaining_time":0.1570346774},
{"learn":[3.367833107],"iteration":787,"passed_time":0.5808202137,"remaining_time":0.1562612758},
{"learn":[3.36450404],"iteration":788,"passed_time":0.581491649,"remaining_time":0.1555066387},
{"learn":[3.361794558],"iteration":789,"passed_time":0.5822305568,"remaining_time":0.154770148},
{"learn":[3.356880529],"iteration":790,"passed_time":0.5832405947,"remaining_time":0.1541052899},
{"learn":[3.353843509],"iteration":791,"passed_time":0.584047517,"remaining_time":0.1533862166},
{"learn":[3.353640253],"iteration":792,"passed_time":0.5846416982,"remaining_time":0.1526113891},
{"learn":[3.353055088],"iteration":793,"passed_time":0.5851667129,"remaining_time":0.1518190716},
{"learn":[3.351415617],"iteration":794,"passed_time":0.5856947287,"remaining_time":0.1510282005},
{"learn":[3.349169061],"iteration":795,"passed_time":0.5862677543,"remaining_time":0.150249525},
{"learn":[3.346211014],"iteration":796,"passed_time":0.5868242731,"remaining_time":0.1494671612},
{"learn":[3.344560452],"iteration":797,"passed_time":0.5874109831,"remaining_time":0.1486930057},
{"learn":[3.344445461],"iteration":798,"passed_time":0.587918845,"remaining_time":0.1478994842},
{"learn":[3.342608898],"iteration":799,"passed_time":0.5887374838,"remaining_time":0.1471843709},
{"learn":[3.339572899],"iteration":800,"passed_time":0.5896053865,"remaining_time":0.1464812384},
{"learn":[3.339309302],"iteration":801,"passed_time":0.590331498,"remaining_time":0.145742689},
{"learn":[3.33698088],"iteration":802,"passed_time":0.5910064033,"remaining_time":0.1449916083},
{"learn":[3.334746342],"iteration":803,"passed_time":0.5915290637,"remaining_time":0.1442036026},
{"learn":[3.332048511],"iteration":804,"passed_time":0.5920367154,"remaining_time":0.1434126205},
{"learn":[3.331932544],"iteration":805,"passed_time":0.592523425,"remaining_time":0.1426173008},
{"learn":[3.330541133],"iteration":806,"passed_time":0.5930155899,"remaining_time":0.1418240506},
{"learn":[3.329124989],"iteration":807,"passed_time":0.593541055,"remaining_time":0.1410394586},
{"learn":[3.32583918],"iteration":808,"passed_time":0.5940996607,"remaining_time":0.1402633315},
{"learn":[3.325287299],"iteration":809,"passed_time":0.5946014625,"remaining_time":0.1394744171},
{"learn":[3.322745162],"iteration":810,"passed_time":0.5951436985,"remaining_time":0.1386956338},
{"learn":[3.319733662],"iteration":811,"passed_time":0.5957455675,"remaining_time":0.1379312398},
{"learn":[3.318080007],"iteration":812,"passed_time":0.5968443933,"remaining_time":0.1372815517},
{"learn":[3.317179538],"iteration":813,"passed_time":0.5976117489,"remaining_time":0.1365550188},
{"learn":[3.315685949],"iteration":814,"passed_time":0.5981930145,"remaining_time":0.1357861444},
{"learn":[3.314944576],"iteration":815,"passed_time":0.5987253947,"remaining_time":0.1350067067},
{"learn":[3.312369052],"iteration":816,"passed_time":0.599246081,"remaining_time":0.1342252544},
{"learn":[3.312321621],"iteration":817,"passed_time":0.599641854,"remaining_time":0.1334166472},
{"learn":[3.309465776],"iteration":818,"passed_time":0.6001365748,"remaining_time":0.1326309158},
{"learn":[3.308307377],"iteration":819,"passed_time":0.6007038423,"remaining_time":0.131861819},
{"learn":[3.308076804],"iteration":820,"passed_time":0.6012326689,"remaining_time":0.1310848328},
{"learn":[3.305643326],"iteration":821,"passed_time":0.6017569634,"remaining_time":0.130307469},
{"learn":[3.304154814],"iteration":822,"passed_time":0.6022585232,"remaining_time":0.1295258306},
{"learn":[3.303076321],"iteration":823,"passed_time":0.6029082005,"remaining_time":0.1287765088},
{"learn":[3.301746372],"iteration":824,"passed_time":0.6039326781,"remaining_time":0.1281069317},
{"learn":[3.301345455],"iteration":825,"passed_time":0.6053037968,"remaining_time":0.1275095165},
{"learn":[3.299181039],"iteration":826,"passed_time":0.6058500906,"remaining_time":0.1267376852},
{"learn":[3.297989357],"iteration":827,"passed_time":0.6063839969,"remaining_time":0.1259638254},
{"learn":[3.294775182],"iteration":828,"passed_time":0.6069089496,"remaining_time":0.1251886977},
{"learn":[3.293840636],"iteration":829,"passed_time":0.6074476963,"remaining_time":0.124416998},
{"learn":[3.289279397],"iteration":830,"passed_time":0.6079636353,"remaining_time":0.1236412207},
{"learn":[3.286204979],"iteration":831,"passed_time":0.6084934668,"remaining_time":0.1228688731},
{"learn":[3.284833593],"iteration":832,"passed_time":0.6090010761,"remaining_time":0.1220926527},
{"learn":[3.283519914],"iteration":833,"passed_time":0.6095147682,"remaining_time":0.1213182872},
{"learn":[3.282853026],"iteration":834,"passed_time":0.6100936441,"remaining_time":0.1205574267},
{"learn":[3.281944673],"iteration":835,"passed_time":0.6111855769,"remaining_time":0.1198976491},
{"learn":[3.279764865],"iteration":836,"passed_time":0.6119852495,"remaining_time":0.1191799231},
{"learn":[3.277468839],"iteration":837,"passed_time":0.6125726926,"remaining_time":0.118420974},
{"learn":[3.277124974],"iteration":838,"passed_time":0.6130728876,"remaining_time":0.1176456912},
{"learn":[3.275636037],"iteration":839,"passed_time":0.6136099489,"remaining_time":0.1168780855},
{"learn":[3.274413635],"iteration":840,"passed_time":0.614126516,"remaining_time":0.1161071534},
{"learn":[3.272636087],"iteration":841,"passed_time":0.6146352017,"remaining_time":0.1153353466},
{"learn":[3.269644466],"iteration":842,"passed_time":0.6151523718,"remaining_time":0.1145657442},
{"learn":[3.26852083],"iteration":843,"passed_time":0.6157203939,"remaining_time":0.1138061392},
{"learn":[3.267820927],"iteration":844,"passed_time":0.6162185708,"remaining_time":0.1130341757},
{"learn":[3.267331099],"iteration":845,"passed_time":0.616757539,"remaining_time":0.1122702849},
{"learn":[3.267231014],"iteration":846,"passed_time":0.6173873888,"remaining_time":0.1115233418},
{"learn":[3.267158695],"iteration":847,"passed_time":0.6181912249,"remaining_time":0.1108078611},
{"learn":[3.264718705],"iteration":848,"passed_time":0.6194843407,"remaining_time":0.1101791937},
{"learn":[3.261678512],"iteration":849,"passed_time":0.620105056,"remaining_time":0.109430304},
{"learn":[3.261368381],"iteration":850,"passed_time":0.6206611255,"remaining_time":0.1086703968},
{"learn":[3.260128799],"iteration":851,"passed_time":0.6211447064,"remaining_time":0.1078983762},
{"learn":[3.258972952],"iteration":852,"passed_time":0.621652302,"remaining_time":0.1071311704},
{"learn":[3.258724846],"iteration":853,"passed_time":0.6222027088,"remaining_time":0.1063718917},
{"learn":[3.25686724],"iteration":854,"passed_time":0.622716092,"remaining_time":0.1056068226},
{"learn":[3.255750259],"iteration":855,"passed_time":0.6232385204,"remaining_time":0.1048438632},
{"learn":[3.254915866],"iteration":856,"passed_time":0.623720152,"remaining_time":0.1040746578},
{"learn":[3.254348625],"iteration":857,"passed_time":0.6243533435,"remaining_time":0.103331206},
{"learn":[3.253408514],"iteration":858,"passed_time":0.6249886103,"remaining_time":0.1025883516},
{"learn":[3.253291714],"iteration":859,"passed_time":0.6257712886,"remaining_time":0.1018697447},
{"learn":[3.250186342],"iteration":860,"passed_time":0.6265445406,"remaining_time":0.1011494671},
{"learn":[3.249141318],"iteration":861,"passed_time":0.6271275543,"remaining_time":0.1003986108},
{"learn":[3.246300388],"iteration":862,"passed_time":0.6276552017,"remaining_time":0.09963935415},
{"learn":[3.245205135],"iteration":863,"passed_time":0.6281921389,"remaining_time":0.09888209594},
{"learn":[3.244403535],"iteration":864,"passed_time":0.6287212127,"remaining_time":0.09812411991},
{"learn":[3.244211781],"iteration":865,"passed_time":0.6292281654,"remaining_time":0.09736324962},
{"learn":[3.242286347],"iteration":866,"passed_time":0.6297599276,"remaining_time":0.0966067709},
{"learn":[3.239606746],"iteration":867,"passed_time":0.6302791826,"remaining_time":0.09584890796},
{"learn":[3.236773361],"iteration":868,"passed_time":0.6307913939,"remaining_time":0.09509053234},
{"learn":[3.234552446],"iteration":869,"passed_time":0.6313124046,"remaining_time":0.09433403746},
{"learn":[3.233724647],"iteration":870,"passed_time":0.6321408418,"remaining_time":0.09362361492},
{"learn":[3.230851485],"iteration":871,"passed_time":0.6331636301,"remaining_time":0.09294145029},
{"learn":[3.227728941],"iteration":872,"passed_time":0.6343680894,"remaining_time":0.09228493396},
{"learn":[3.225787575],"iteration":873,"passed_time":0.634876095,"remaining_time":0.09152675969},
{"learn":[3.222797487],"iteration":874,"passed_time":0.6354102189,"remaining_time":0.09077288841},
{"learn":[3.22137014],"iteration":875,"passed_time":0.6359171864,"remaining_time":0.09001567478},
{"learn":[3.219701963],"iteration":876,"passed_time":0.63644596,"remaining_time":0.08926209018},
{"learn":[3.21783327],"iteration":877,"passed_time":0.6369917502,"remaining_time":0.08851138214},
{"learn":[3.217713355],"iteration":878,"passed_time":0.6375208041,"remaining_time":0.08775883651},
{"learn":[3.217666091],"iteration":879,"passed_time":0.6380170882,"remaining_time":0.08700233021},
{"learn":[3.214962005],"iteration":880,"passed_time":0.6385352948,"remaining_time":0.0862493758},
{"learn":[3.214081828],"iteration":881,"passed_time":0.6391797534,"remaining_time":0.08551384455},
{"learn":[3.213358337],"iteration":882,"passed_time":0.6400939001,"remaining_time":0.08481425404},
{"learn":[3.210850401],"iteration":883,"passed_time":0.6409037274,"remaining_time":0.08410048911},
{"learn":[3.207810328],"iteration":884,"passed_time":0.6414830516,"remaining_time":0.08335655473},
{"learn":[3.204935073],"iteration":885,"passed_time":0.6420455747,"remaining_time":0.08261083016},
{"learn":[3.20280198],"iteration":886,"passed_time":0.6425866134,"remaining_time":0.08186278165},
{"learn":[3.200663495],"iteration":887,"passed_time":0.643119451,"remaining_time":0.08111416499},
{"learn":[3.197301669],"iteration":888,"passed_time":0.6436305165,"remaining_time":0.08036331534},
{"learn":[3.195666943],"iteration":889,"passed_time":0.6441441485,"remaining_time":0.07961332172},
{"learn":[3.193886506],"iteration":890,"passed_time":0.6446989921,"remaining_time":0.07886890027},
{"learn":[3.190601248],"iteration":891,"passed_time":0.6452526067,"remaining_time":0.07812475507},
{"learn":[3.188983797],"iteration":892,"passed_time":0.6460129128,"remaining_time":0.07740580254},
{"learn":[3.187365749],"iteration":893,"passed_time":0.6467629203,"remaining_time":0.07668553641},
{"learn":[3.186160771],"iteration":894,"passed_time":0.6475804132,"remaining_time":0.0759731211},
{"learn":[3.185358981],"iteration":895,"passed_time":0.6484062776,"remaining_time":0.07526144293},
{"learn":[3.183832164],"iteration":896,"passed_time":0.6490625943,"remaining_time":0.07453004149},
{"learn":[3.183106966],"iteration":897,"passed_time":0.649592751,"remaining_time":0.07378447728},
{"learn":[3.182838152],"iteration":898,"passed_time":0.6501007701,"remaining_time":0.07303690521},
{"learn":[3.180835453],"iteration":899,"passed_time":0.6506785211,"remaining_time":0.07229761345},
{"learn":[3.179957348],"iteration":900,"passed_time":0.6512077476,"remaining_time":0.07155334852},
{"learn":[3.179752966],"iteration":901,"passed_time":0.6517009285,"remaining_time":0.07080564411},
{"learn":[3.178851983],"iteration":902,"passed_time":0.6521968696,"remaining_time":0.07005879995},
{"learn":[3.176748586],"iteration":903,"passed_time":0.6527230479,"remaining_time":0.0693157219},
{"learn":[3.172960988],"iteration":904,"passed_time":0.6532583918,"remaining_time":0.06857408533},
{"learn":[3.172794225],"iteration":905,"passed_time":0.653904793,"remaining_time":0.06784442665},
{"learn":[3.169996507],"iteration":906,"passed_time":0.6548081339,"remaining_time":0.06714129708},
{"learn":[3.16813015],"iteration":907,"passed_time":0.655844577,"remaining_time":0.06645121265},
{"learn":[3.166920871],"iteration":908,"passed_time":0.6565333682,"remaining_time":0.06572556271},
{"learn":[3.16531606],"iteration":909,"passed_time":0.6570577938,"remaining_time":0.06498373785},
{"learn":[3.162035247],"iteration":910,"passed_time":0.6575738273,"remaining_time":0.0642415704},
{"learn":[3.16189467],"iteration":911,"passed_time":0.6580788075,"remaining_time":0.06349883231},
{"learn":[3.161008416],"iteration":912,"passed_time":0.6586854206,"remaining_time":0.06276629966},
{"learn":[3.160560787],"iteration":913,"passed_time":0.6592005764,"remaining_time":0.06202543716},
{"learn":[3.160416261],"iteration":914,"passed_time":0.6598191356,"remaining_time":0.0612946738},
{"learn":[3.15844291],"iteration":915,"passed_time":0.6603693413,"remaining_time":0.06055788719},
{"learn":[3.155040501],"iteration":916,"passed_time":0.6609580546,"remaining_time":0.05982499295},
{"learn":[3.154937548],"iteration":917,"passed_time":0.6616081771,"remaining_time":0.05909789817},
{"learn":[3.153721161],"iteration":918,"passed_time":0.6625870252,"remaining_time":0.05839994455},
{"learn":[3.153170511],"iteration":919,"passed_time":0.6633907219,"remaining_time":0.05768614973},
{"learn":[3.153113601],"iteration":920,"passed_time":0.6641354935,"remaining_time":0.05696710531},
{"learn":[3.150607379],"iteration":921,"passed_time":0.6646941286,"remaining_time":0.05623225816},
{"learn":[3.148408359],"iteration":922,"passed_time":0.6652516643,"remaining_time":0.05549770114},
{"learn":[3.147495728],"iteration":923,"passed_time":0.6658078325,"remaining_time":0.0547634148},
{"learn":[3.146946235],"iteration":924,"passed_time":0.6663319563,"remaining_time":0.05402691538},
{"learn":[3.14472738],"iteration":925,"passed_time":0.6668490168,"remaining_time":0.05329031019},
{"learn":[3.144469477],"iteration":926,"passed_time":0.6673487435,"remaining_time":0.05255281367},
{"learn":[3.142975516],"iteration":927,"passed_time":0.6678666326,"remaining_time":0.05181723873},
{"learn":[3.14079113],"iteration":928,"passed_time":0.668511615,"remaining_time":0.05109184571},
{"learn":[3.138173032],"iteration":929,"passed_time":0.669434312,"remaining_time":0.05038752886},
{"learn":[3.136352813],"iteration":930,"passed_time":0.6705258125,"remaining_time":0.04969525356},
{"learn":[3.133735004],"iteration":931,"passed_time":0.6712732799,"remaining_time":0.04897702042},
{"learn":[3.1319496],"iteration":932,"passed_time":0.6718720659,"remaining_time":0.0482480476},
{"learn":[3.129865343],"iteration":933,"passed_time":0.6724180871,"remaining_time":0.047515625},
{"learn":[3.129830206],"iteration":934,"passed_time":0.6728085482,"remaining_time":0.04677278677},
{"learn":[3.126676562],"iteration":935,"passed_time":0.6733398577,"remaining_time":0.04604033215},
{"learn":[3.12645665],"iteration":936,"passed_time":0.6739147057,"remaining_time":0.04531123421},
{"learn":[3.126378007],"iteration":937,"passed_time":0.6744726137,"remaining_time":0.04458134547},
{"learn":[3.124621914],"iteration":938,"passed_time":0.6750358934,"remaining_time":0.04385217199},
{"learn":[3.123379018],"iteration":939,"passed_time":0.6756582344,"remaining_time":0.04312712134},
{"learn":[3.123332451],"iteration":940,"passed_time":0.6763182332,"remaining_time":0.04240465011},
{"learn":[3.122432444],"iteration":941,"passed_time":0.6773058889,"remaining_time":0.04170248573},
{"learn":[3.121889006],"iteration":942,"passed_time":0.6780461078,"remaining_time":0.04098475943},
{"learn":[3.121070914],"iteration":943,"passed_time":0.6786219412,"remaining_time":0.0402572338},
{"learn":[3.118444705],"iteration":944,"passed_time":0.6791385475,"remaining_time":0.03952658213},
{"learn":[3.116820458],"iteration":945,"passed_time":0.6796708863,"remaining_time":0.03879728104},
{"learn":[3.114971041],"iteration":946,"passed_time":0.6801964259,"remaining_time":0.03806801539},
{"learn":[3.114685138],"iteration":947,"passed_time":0.6807605448,"remaining_time":0.03734129571},
{"learn":[3.113399363],"iteration":948,"passed_time":0.6813028518,"remaining_time":0.03661374651},
{"learn":[3.110575399],"iteration":949,"passed_time":0.681954996,"remaining_time":0.03589236821},
{"learn":[3.110466553],"iteration":950,"passed_time":0.6824578767,"remaining_time":0.03516344475},
{"learn":[3.108691641],"iteration":951,"passed_time":0.6830261798,"remaining_time":0.03443829478},
{"learn":[3.107898017],"iteration":952,"passed_time":0.6837035557,"remaining_time":0.03371885322},
{"learn":[3.105551729],"iteration":953,"passed_time":0.6846435719,"remaining_time":0.03301216384},
{"learn":[3.104824945],"iteration":954,"passed_time":0.6853196827,"remaining_time":0.03229255049},
{"learn":[3.103186704],"iteration":955,"passed_time":0.6859285244,"remaining_time":0.03156993209},
{"learn":[3.102330655],"iteration":956,"passed_time":0.6864382953,"remaining_time":0.0308431},
{"learn":[3.102291298],"iteration":957,"passed_time":0.6869226084,"remaining_time":0.03011560496},
{"learn":[3.100363529],"iteration":958,"passed_time":0.6874202264,"remaining_time":0.0293891859},
{"learn":[3.097871596],"iteration":959,"passed_time":0.6880719691,"remaining_time":0.02866966538},
{"learn":[3.097372213],"iteration":960,"passed_time":0.6886112622,"remaining_time":0.0279457224},
{"learn":[3.095981813],"iteration":961,"passed_time":0.6891476462,"remaining_time":0.0272220484},
{"learn":[3.095347452],"iteration":962,"passed_time":0.689696186,"remaining_time":0.02649923041},
{"learn":[3.094728409],"iteration":963,"passed_time":0.6902850887,"remaining_time":0.02577828132},
{"learn":[3.094118537],"iteration":964,"passed_time":0.6910099422,"remaining_time":0.02506253676},
{"learn":[3.093793695],"iteration":965,"passed_time":0.6918489333,"remaining_time":0.02435079061},
{"learn":[3.092581602],"iteration":966,"passed_time":0.6925409383,"remaining_time":0.02363376521},
{"learn":[3.091694202],"iteration":967,"passed_time":0.6931505526,"remaining_time":0.02291406786},
{"learn":[3.090298312],"iteration":968,"passed_time":0.6936913461,"remaining_time":0.02219239601},
{"learn":[3.090020107],"iteration":969,"passed_time":0.6943036674,"remaining_time":0.0214733093},
{"learn":[3.088949869],"iteration":970,"passed_time":0.6947978318,"remaining_time":0.02075091362},
{"learn":[3.086700204],"iteration":971,"passed_time":0.6953115136,"remaining_time":0.02002954977},
{"learn":[3.086584317],"iteration":972,"passed_time":0.6958068492,"remaining_time":0.01930810373},
{"learn":[3.084850742],"iteration":973,"passed_time":0.6962994361,"remaining_time":0.0185870486},
{"learn":[3.084239948],"iteration":974,"passed_time":0.6968037513,"remaining_time":0.01786676285},
{"learn":[3.082561673],"iteration":975,"passed_time":0.6973430615,"remaining_time":0.0171477802},
{"learn":[3.07991814],"iteration":976,"passed_time":0.6979970914,"remaining_time":0.01643186602},
{"learn":[3.079350277],"iteration":977,"passed_time":0.6989365856,"remaining_time":0.01572249988},
{"learn":[3.077637462],"iteration":978,"passed_time":0.699931673,"remaining_time":0.01501385611},
{"learn":[3.076733301],"iteration":979,"passed_time":0.7005753727,"remaining_time":0.01429745659},
{"learn":[3.07594065],"iteration":980,"passed_time":0.7011423111,"remaining_time":0.01357971856},
{"learn":[3.072594655],"iteration":981,"passed_time":0.7017304764,"remaining_time":0.01286267676},
{"learn":[3.071977674],"iteration":982,"passed_time":0.7022214707,"remaining_time":0.01214421669},
{"learn":[3.069532634],"iteration":983,"passed_time":0.7027619601,"remaining_time":0.01142702374},
{"learn":[3.068870784],"iteration":984,"passed_time":0.7033023804,"remaining_time":0.01071018853},
{"learn":[3.068801463],"iteration":985,"passed_time":0.7037985659,"remaining_time":0.009993083085},
{"learn":[3.067433249],"iteration":986,"passed_time":0.7043556481,"remaining_time":0.009277227382},
{"learn":[3.065611456],"iteration":987,"passed_time":0.7048589689,"remaining_time":0.008561040108},
{"learn":[3.063039162],"iteration":988,"passed_time":0.7054689908,"remaining_time":0.00784647007},
{"learn":[3.06177873],"iteration":989,"passed_time":0.7065320449,"remaining_time":0.007136687322},
{"learn":[3.061689148],"iteration":990,"passed_time":0.7071979326,"remaining_time":0.006422584655},
{"learn":[3.058984039],"iteration":991,"passed_time":0.7078455159,"remaining_time":0.00570843158},
{"learn":[3.057492984],"iteration":992,"passed_time":0.7084253939,"remaining_time":0.004993935305},
{"learn":[3.057290731],"iteration":993,"passed_time":0.7089370357,"remaining_time":0.004279298002},
{"learn":[3.056068348],"iteration":994,"passed_time":0.7094546349,"remaining_time":0.003565098668},
{"learn":[3.054987307],"iteration":995,"passed_time":0.7099964453,"remaining_time":0.002851391347},
{"learn":[3.054200234],"iteration":996,"passed_time":0.7105148293,"remaining_time":0.002137958363},
{"learn":[3.052732869],"iteration":997,"passed_time":0.7110302515,"remaining_time":0.001424910324},
{"learn":[3.051787862],"iteration":998,"passed_time":0.7115941631,"remaining_time":0.0007123064696},
{"learn":[3.051366222],"iteration":999,"passed_time":0.7121327402,"remaining_time":0}
]}